Workbook

Sheet sizing
C1: Workload (TPS) | D1: Core per Server | E1: Max Server Faults | F1: HA Ratio
C2: 8000 | D2: ='x86 TCO'!G5 -> 40 | E2: 2 | F2: =E4/D4 -> 0.2
B3: Typical core Ratio | C3: TPS by Core | D3: # of Cores for workload TPS | E3: HA cores | F3: Prod cores | H3: Dev % of Workload | I3: Dev cores | J3: Test % of Workload | K3: Test cores | L3: PreProd % of Workload | M3: PreProd cores | N3: DR active cores % of Prod+PreProd | O3: DR cores | P3: DR CBU (spare) cores | R3: Tot # of Active cores | S3: x86 to z Active Core ratio | T3: Tot # of Active cores no DR | U3: x86 to z Core ratio no DR | V3: Tot # of cores | W3: x86 to z Core ratio
A4: x86 | B4: 10 | C4: 20 | D4: =ROUNDUP($C$2/$C4,0) -> 400 | E4: =IF(E2*D2>D4,D4,E2*D2) -> 80 | F4: =D4+E4 -> 480 | H4: 0.5 | I4: =ROUNDUP($F4*H4,0) -> 240 | J4: =H4 -> 0.5 | K4: =ROUNDUP($F4*J4,0) -> 240 | L4: 1 | M4: =ROUNDUP($F4*L4,0) -> 480 | N4: 1 | O4: =ROUNDUP(($F4+M4)*N4,0) -> 960 | R4: =F4+I4+K4+M4+O4 -> 2400 | S4: =R$4/R5 -> 20 | T4: =F4+I4+K4+M4 -> 1440 | U4: =T$4/T5 -> 12 | V4: =R4 -> 2400 | W4: =V$4/V5 -> 12
A5: LinuxONE | B5: 1 | C5: =$C$4*B4 -> 200 | D5: =ROUNDUP($C$2/$C5,0) -> 40 | F5: =D5+E5 -> 40 | H5: =H4 -> 0.5 | I5: =ROUNDUP($F5*H5,0) -> 20 | J5: =J4 -> 0.5 | K5: =ROUNDUP($F5*J5,0) -> 20 | L5: 1 | M5: =ROUNDUP($F5*L5,0) -> 40 | P5: =F5+M5 -> 80 | R5: =F5+I5+K5+M5+O5 -> 120 | T5: =F5+I5+K5+M5 -> 120 | V5: =R5+P5 -> 200
L6: * most customers would have exact replica of Prod
A7: Sizing Disclaimer:
A8: Calculation of required cores for a real workload requires sophisticated analysis.
A9: In order to make a simple and realistic sizing, for this exercise a simplified approach is used considering the Typical core ratio.
A10: The typical core ratio take into account:
A11: Architecture, GHz & utilization, VM & Hypervisor effect, System Overhead, Networking co-location effect, Sysplex, etc.
A12: Although these data will change slightly depending the server model used, these data averages are proved by many real workloads and documented also on papers such as those reported in the references.
A13: Reference: A. Micarelli, S. Proietti Conti, "Why Application Requirements Should Drive the Choice of your Infrastructure", 2021 IBM Corporation web published paper
A14: Download at: | B14: https://www.ibm.com/downloads/cas/2VVYYVNP
A16: Legend:
B17: Input field
B18: Optional input
B19: Suggested input (reccomended not change)
B20: Calculated values
B21: Calculated values highlighted (Very Important)
B22: Calculated values highlighted (Important)
B23: Constant

Sheet x86 TCO
A1: Small Size Enterprise | R1: Acquisition Cost | W1: Maintenance/ Operating Cost | AB1: TOTALS
A2: Typically x86 workload | R2: 1 | S2: 2 | T2: 3 | U2: 4 | V2: 5 | W2: 1 | X2: 2 | Y2: 3 | Z2: 4 | AA2: 5
A3: Hardware
A4: Server Model | C4: Acquisition Cost | D4: Maintenance/ Operating Cost | E4: Starting Year of Maint | F4: Discount % | G4: # of Cores per Server | H4: # of Sockets | I4: # of Cores per socket | J4: # of "boxes" per Rack | L4: kW
A5: {=INDEX(A6:A16,$B$5)} -> Rack HPE w Xeon Gold 6230 20C 2.10GHz (2 Chips, 40 Cores) | B5: =MATCH("S",B6:B16) -> 6 | C5: {=INDEX(C6:C16,$B$5)} -> 8000 | D5: {=INDEX(D6:D16,$B$5)} -> 1600 | E5: {=INDEX(E6:E16,$B$5)} -> 4 | F5: {=INDEX(F6:F16,$B$5)} -> 0 | G5: {=INDEX(G6:G16,$B$5)} -> 40 | H5: {=INDEX(H6:H16,$B$5)} -> 2 | I5: {=INDEX(I6:I16,$B$5)} -> 20 | J5: {=INDEX(J6:J16,$B$5)} -> 15 | L5: {=INDEX(L6:L16,$B$5)} -> 1.6
A6: Rack server w Xeon Gold 6244 8C 3.60GHz (2 Chips, 16 Cores) | B6: 0 | C6: 8000 | D6: =C6*0.2 -> 1600 | E6: 4 | F6: 0.3 | G6: =H6*I6 -> 16 | H6: 2 | I6: 8 | J6: 30 | L6: 0.5
A7: Rack server w Xeon Gold 5115 10C 2.40GHz (2 Chips, 20 Cores) | B7: 0 | C7: 10000 | D7: =C7*0.2 -> 2000 | E7: 4 | F7: 0.3 | G7: =H7*I7 -> 20 | H7: 2 | I7: 10 | J7: 30 | L7: 0.6
A8: Rack server w Xeon Gold 6146 12C 3.20GHz (2 Chips, 24 Cores) | B8: 0 | C8: 12000 | D8: =C8*0.2 -> 2400 | E8: 4 | F8: 0.3 | G8: =H8*I8 -> 24 | H8: 2 | I8: 12 | J8: 15 | L8: 1.2
A9: Rack server w Xeon Gold 6146 12C 3.20GHz (4 Chips, 48 Cores) | B9: 0 | C9: 24000 | D9: =C9*0.2 -> 4800 | E9: 4 | F9: 0.3 | G9: =H9*I9 -> 48 | H9: 4 | I9: 12 | J9: 15 | L9: 1.2
A10: =Data!A5 -> Rack DELL w Xeon Gold 5220 18C 2.20GHz (4 Chips, 72 Cores) | B10: 0 | C10: =Data!B5 -> 20800 | D10: =Data!C5 -> 4160 | E10: =Data!D5 -> 4 | F10: =Data!E5 -> 0.37 | G10: =H10*I10 -> 72 | H10: =Data!G5 -> 4 | I10: =Data!H5 -> 18 | J10: =Data!I5 -> 10 | L10: =Data!J5 -> 1.1
A11: =Data!A6 -> Rack HPE w Xeon Gold 6230 20C 2.10GHz (2 Chips, 40 Cores) | B11: S | C11: =Data!B6 -> 8000 | D11: =Data!C6 -> 1600 | E11: =Data!D6 -> 4 | F11: =Data!E6 -> 0 | G11: =H11*I11 -> 40 | H11: =Data!G6 -> 2 | I11: =Data!H6 -> 20 | J11: =Data!I6 -> 15 | L11: =Data!J6 -> 1.6
B12: 0 | G12: =H12*I12 -> 0
B13: 0 | G13: =H13*I13 -> 0
B14: 0 | G14: =H14*I14 -> 0
B15: 0 | G15: =H15*I15 -> 0
B16: 0 | G16: =H16*I16 -> 0
A18: Environment being investigated | C18: # of Cores for bare workload | D18: % of Cores vs bare workload | E18: Allocated Cores | F18: cores per Server | G18: Allocated Servers | H18: Tot cores available | I18: Spare Cores | J18: % of spare cores | K18: Allocated Sockets | O18: # of Server | P18: # of Sockets | Q18: # of Cores | R18: 1 | S18: 2 | T18: 3 | U18: 4 | V18: 5 | W18: 1 | X18: 2 | Y18: 3 | Z18: 4 | AA18: 5 | AB18: TOT
A19: Prod | C19: =sizing!D4 -> 400 | D19: see sizing | E19: =sizing!F4 -> 480 | F19: =$G$5 -> 40 | G19: =ROUNDUP(E19/F19,0) -> 12 | H19: =F19*G19 -> 480 | I19: =H19-E19 -> 0 | J19: =I19/H19 -> 0 | K19: =ROUNDUP(E19/$I$5,0) -> 24 | N19: Prod | O19: =G19 -> 12 | P19: =K19 -> 24 | Q19: =E19 -> 480 | R19: =$O19*$C$5*(1-$F$5) -> 96000 | W19: =IF(W$18<$E$5,0,$O19*$D$5)*(1-$F$5) -> 0 | X19: =IF(X$18<$E$5,0,$O19*$D$5)*(1-$F$5) -> 0 | Y19: =IF(Y$18<$E$5,0,$O19*$D$5)*(1-$F$5) -> 0 | Z19: =IF(Z$18<$E$5,0,$O19*$D$5)*(1-$F$5) -> 19200 | AA19: =IF(AA$18<$E$5,0,$O19*$D$5)*(1-$F$5) -> 19200 | AB19: =SUM(R19:AA19) -> 134400 | AC19: Prod
A20: Dev | D20: =sizing!H4 -> 0.5 | E20: =sizing!I4 -> 240 | F20: =$G$5 -> 40 | G20: =ROUNDUP(E20/F20,0) -> 6 | H20: =F20*G20 -> 240 | I20: =H20-E20 -> 0 | J20: =I20/H20 -> 0 | K20: =ROUNDUP(E20/$I$5,0) -> 12 | N20: Dev | O20: =G20 -> 6 | P20: =K20 -> 12 | Q20: =E20 -> 240 | R20: =$O20*$C$5*(1-$F$5) -> 48000 | W20: =IF(W$18<$E$5,0,$O20*$D$5)*(1-$F$5) -> 0 | X20: =IF(X$18<$E$5,0,$O20*$D$5)*(1-$F$5) -> 0 | Y20: =IF(Y$18<$E$5,0,$O20*$D$5)*(1-$F$5) -> 0 | Z20: =IF(Z$18<$E$5,0,$O20*$D$5)*(1-$F$5) -> 9600 | AA20: =IF(AA$18<$E$5,0,$O20*$D$5)*(1-$F$5) -> 9600 | AB20: =SUM(R20:AA20) -> 67200 | AC20: Dev
A21: Test | D21: =sizing!J4 -> 0.5 | E21: =sizing!K4 -> 240 | F21: =$G$5 -> 40 | G21: =ROUNDUP(E21/F21,0) -> 6 | H21: =F21*G21 -> 240 | I21: =H21-E21 -> 0 | J21: =I21/H21 -> 0 | K21: =ROUNDUP(E21/$I$5,0) -> 12 | N21: Test | O21: =G21 -> 6 | P21: =K21 -> 12 | Q21: =E21 -> 240 | R21: =$O21*$C$5*(1-$F$5) -> 48000 | W21: =IF(W$18<$E$5,0,$O21*$D$5)*(1-$F$5) -> 0 | X21: =IF(X$18<$E$5,0,$O21*$D$5)*(1-$F$5) -> 0 | Y21: =IF(Y$18<$E$5,0,$O21*$D$5)*(1-$F$5) -> 0 | Z21: =IF(Z$18<$E$5,0,$O21*$D$5)*(1-$F$5) -> 9600 | AA21: =IF(AA$18<$E$5,0,$O21*$D$5)*(1-$F$5) -> 9600 | AB21: =SUM(R21:AA21) -> 67200 | AC21: Test
A22: PreProd | D22: =sizing!L4 -> 1 | E22: =sizing!M4 -> 480 | F22: =$G$5 -> 40 | G22: =ROUNDUP(E22/F22,0) -> 12 | H22: =F22*G22 -> 480 | I22: =H22-E22 -> 0 | J22: =I22/H22 -> 0 | K22: =ROUNDUP(E22/$I$5,0) -> 24 | N22: PreProd | O22: =G22 -> 12 | P22: =K22 -> 24 | Q22: =E22 -> 480 | R22: =$O22*$C$5*(1-$F$5) -> 96000 | W22: =IF(W$18<$E$5,0,$O22*$D$5)*(1-$F$5) -> 0 | X22: =IF(X$18<$E$5,0,$O22*$D$5)*(1-$F$5) -> 0 | Y22: =IF(Y$18<$E$5,0,$O22*$D$5)*(1-$F$5) -> 0 | Z22: =IF(Z$18<$E$5,0,$O22*$D$5)*(1-$F$5) -> 19200 | AA22: =IF(AA$18<$E$5,0,$O22*$D$5)*(1-$F$5) -> 19200 | AB22: =SUM(R22:AA22) -> 134400 | AC22: QA
A23: DR | D23: =sizing!N4 -> 1 | E23: =sizing!O4 -> 960 | F23: =$G$5 -> 40 | G23: =G19+G22 -> 24 | H23: =F23*G23 -> 960 | I23: =H23-E23 -> 0 | J23: =I23/H23 -> 0 | K23: =ROUNDUP(E23/$I$5,0) -> 48 | N23: DR | O23: =G23 -> 24 | P23: =K23 -> 48 | Q23: =E23 -> 960 | R23: =$O23*$C$5*(1-$F$5) -> 192000 | W23: =IF(W$18<$E$5,0,$O23*$D$5)*(1-$F$5) -> 0 | X23: =IF(X$18<$E$5,0,$O23*$D$5)*(1-$F$5) -> 0 | Y23: =IF(Y$18<$E$5,0,$O23*$D$5)*(1-$F$5) -> 0 | Z23: =IF(Z$18<$E$5,0,$O23*$D$5)*(1-$F$5) -> 38400 | AA23: =IF(AA$18<$E$5,0,$O23*$D$5)*(1-$F$5) -> 38400 | AB23: =SUM(R23:AA23) -> 268800 | AC23: DR
A24: TOT | E24: =SUM(E19:E23) -> 2400 | G24: =SUM(G19:G23) -> 60 | H24: =SUM(H19:H23) -> 2400 | I24: =SUM(I19:I23) -> 0 | J24: =I24/H24 -> 0 | K24: =SUM(K19:K23) -> 120 | O24: =SUM(O19:O23) -> 60 | P24: =SUM(P19:P23) -> 120 | Q24: =SUM(Q19:Q23) -> 2400 | R24: =SUM(R19:R23) -> 480000 | S24: =SUM(S19:S23) -> 0 | T24: =SUM(T19:T23) -> 0 | U24: =SUM(U19:U23) -> 0 | V24: =SUM(V19:V23) -> 0 | ... AB24: =SUM(AB19:AB23) -> 672000 | AC24: TOT
O25: # of Server | P25: # of Sockets | Q25: # of Cores
A26: Software Stack
A27: Production | C27: Acquisition/ Capital Cost | D27: Maintenance/ Operating Cost | E27: Starting Year of yearly charges | F27: Discount % | G27: Unit of Measure | H27: Measured by | I27: conversion factor | J27: server | K27: socket | L27: core | O27: count | P27: Unit of Measure | Q27: Units | R27: 1 | S27: 2 | T27: 3 | U27: 4 | V27: 5 | W27: 1 | X27: 2 | Y27: 3 | Z27: 4 | AA27: 5 | AB27: TOT
A28: OS | D28: 2000 | E28: 1 | F28: 0.2 | G28: socket | H28: socket | I28: 1 | J28: =$O$19 -> 12 | K28: =$P$19 -> 24 | L28: =$Q$19 -> 480 | O28: =_xlfn.XLOOKUP($H28,$J$27:$L$27,$J28:$L28) -> 24 | P28: socket | Q28: =I28*O28 -> 24 | R28: =$Q28*$C28*(1-$F28) -> 0 | W28: =IF(W$18<$E28,0,$Q28*$D28)*(1-$F28) -> 38400 | X28: =IF(X$18<$E28,0,$Q28*$D28)*(1-$F28) -> 38400 | Y28: =IF(Y$18<$E28,0,$Q28*$D28)*(1-$F28) -> 38400 | Z28: =IF(Z$18<$E28,0,$Q28*$D28)*(1-$F28) -> 38400 | AA28: =IF(AA$18<$E28,0,$Q28*$D28)*(1-$F28) -> 38400 | AB28: =SUM(R28:AA28) -> 192000
A29: VM | C29: 5000 | D29: =C29*0.2 -> 1000 | E29: 2 | F29: 0.2 | G29: socket | H29: socket | I29: 1 | J29: =J28 -> 12 | K29: =K28 -> 24 | L29: =L28 -> 480 | O29: =_xlfn.XLOOKUP($H29,$J$27:$L$27,$J29:$L29) -> 24 | P29: socket | Q29: =I29*O29 -> 24 | R29: =$Q29*$C29*(1-$F29) -> 96000 | W29: =IF(W$18<$E29,0,$Q29*$D29)*(1-$F29) -> 0 | X29: =IF(X$18<$E29,0,$Q29*$D29)*(1-$F29) -> 19200 | Y29: =IF(Y$18<$E29,0,$Q29*$D29)*(1-$F29) -> 19200 | Z29: =IF(Z$18<$E29,0,$Q29*$D29)*(1-$F29) -> 19200 | AA29: =IF(AA$18<$E29,0,$Q29*$D29)*(1-$F29) -> 19200 | AB29: =SUM(R29:AA29) -> 172800
A30: Application Server | C30: =Data!B12 -> 46.82 | D30: =Data!C12 -> 9.36 | E30: =Data!D12 -> 2 | F30: 0.75 | G30: =Data!E12 -> PVU | H30: =Data!F12 -> core | I30: 70 | J30: =J29 -> 12 | K30: =K29 -> 24 | L30: =L29 -> 480 | O30: =_xlfn.XLOOKUP($H30,$J$27:$L$27,$J30:$L30) -> 480 | P30: PVU | Q30: =I30*O30 -> 33600 | R30: =$Q30*$C30*(1-$F30) -> 393288 | W30: =IF(W$18<$E30,0,$Q30*$D30)*(1-$F30) -> 0 | X30: =IF(X$18<$E30,0,$Q30*$D30)*(1-$F30) -> 78624 | Y30: =IF(Y$18<$E30,0,$Q30*$D30)*(1-$F30) -> 78624 | Z30: =IF(Z$18<$E30,0,$Q30*$D30)*(1-$F30) -> 78624 | AA30: =IF(AA$18<$E30,0,$Q30*$D30)*(1-$F30) -> 78624 | AB30: =SUM(R30:AA30) -> 707784
A31: DB | C31: =Data!B25 -> 0 | D31: =Data!C25 -> 8500 | E31: =Data!D25 -> 1 | F31: 0 | G31: =Data!E25 -> server | H31: =Data!F25 -> server | I31: 1 | J31: =J30 -> 12 | K31: =K30 -> 24 | L31: =L30 -> 480 | O31: =_xlfn.XLOOKUP($H31,$J$27:$L$27,$J31:$L31) -> 12 | P31: core | Q31: =I31*O31 -> 12 | R31: =$Q31*$C31*(1-$F31) -> 0 | W31: =IF(W$18<$E31,0,$Q31*$D31)*(1-$F31) -> 102000 | X31: =IF(X$18<$E31,0,$Q31*$D31)*(1-$F31) -> 102000 | Y31: =IF(Y$18<$E31,0,$Q31*$D31)*(1-$F31) -> 102000 | Z31: =IF(Z$18<$E31,0,$Q31*$D31)*(1-$F31) -> 102000 | AA31: =IF(AA$18<$E31,0,$Q31*$D31)*(1-$F31) -> 102000 | AB31: =SUM(R31:AA31) -> 510000
A32: Data Replication Tools | D32: 3000 | E32: 1 | F32: 0.75 | G32: core | H32: core | I32: 0.5 | J32: =J31 -> 12 | K32: =K31 -> 24 | L32: =L31 -> 480 | O32: =_xlfn.XLOOKUP($H32,$J$27:$L$27,$J32:$L32) -> 480 | P32: core | Q32: =I32*O32 -> 240 | R32: =$Q32*$C32*(1-$F32) -> 0 | W32: =IF(W$18<$E32,0,$Q32*$D32)*(1-$F32) -> 180000 | X32: =IF(X$18<$E32,0,$Q32*$D32)*(1-$F32) -> 180000 | Y32: =IF(Y$18<$E32,0,$Q32*$D32)*(1-$F32) -> 180000 | Z32: =IF(Z$18<$E32,0,$Q32*$D32)*(1-$F32) -> 180000 | AA32: =IF(AA$18<$E32,0,$Q32*$D32)*(1-$F32) -> 180000 | AB32: =SUM(R32:AA32) -> 900000
A33: Monitoring Tools | C33: 5000 | D33: =C33*0.2 -> 1000 | E33: 2 | F33: 0.4 | G33: server | H33: server | I33: 1 | J33: =J32 -> 12 | K33: =K32 -> 24 | L33: =L32 -> 480 | O33: =_xlfn.XLOOKUP($H33,$J$27:$L$27,$J33:$L33) -> 12 | P33: server | Q33: =I33*O33 -> 12 | R33: =$Q33*$C33*(1-$F33) -> 36000 | W33: =IF(W$18<$E33,0,$Q33*$D33)*(1-$F33) -> 0 | X33: =IF(X$18<$E33,0,$Q33*$D33)*(1-$F33) -> 7200 | Y33: =IF(Y$18<$E33,0,$Q33*$D33)*(1-$F33) -> 7200 | Z33: =IF(Z$18<$E33,0,$Q33*$D33)*(1-$F33) -> 7200 | AA33: =IF(AA$18<$E33,0,$Q33*$D33)*(1-$F33) -> 7200 | AB33: =SUM(R33:AA33) -> 64800
A34: Security Tools | C34: 5000 | D34: =C34*0.2 -> 1000 | E34: 2 | F34: 0.4 | G34: server | H34: server | I34: 1 | J34: =J33 -> 12 | K34: =K33 -> 24 | L34: =L33 -> 480 | O34: =_xlfn.XLOOKUP($H34,$J$27:$L$27,$J34:$L34) -> 12 | P34: server | Q34: =I34*O34 -> 12 | R34: =$Q34*$C34*(1-$F34) -> 36000 | W34: =IF(W$18<$E34,0,$Q34*$D34)*(1-$F34) -> 0 | X34: =IF(X$18<$E34,0,$Q34*$D34)*(1-$F34) -> 7200 | Y34: =IF(Y$18<$E34,0,$Q34*$D34)*(1-$F34) -> 7200 | Z34: =IF(Z$18<$E34,0,$Q34*$D34)*(1-$F34) -> 7200 | AA34: =IF(AA$18<$E34,0,$Q34*$D34)*(1-$F34) -> 7200 | AB34: =SUM(R34:AA34) -> 64800
Q35: PROD | R35: =SUM(R28:R34) -> 561288 | S35: =SUM(S28:S34) -> 0 | T35: =SUM(T28:T34) -> 0 | U35: =SUM(U28:U34) -> 0 | V35: =SUM(V28:V34) -> 0 | W35: =SUM(W28:W34) -> 320400 | X35: =SUM(X28:X34) -> 432624 | Y35: =SUM(Y28:Y34) -> 432624 | ... AB35: =SUM(AB28:AB34) -> 2612184
A37: Dev | C37: Acquisition/ Capital Cost | D37: Maintenance/ Operating Cost | E37: =E27 -> Starting Year of yearly charges | F37: Discount % | G37: Unit of Measure | H37: Measured by | I37: conversion factor | J37: server | K37: socket | L37: core | O37: count | P37: Unit of Measure | Q37: Units | R37: 1 | S37: 2 | T37: 3 | U37: 4 | V37: 5 | W37: 1 | X37: 2 | Y37: 3 | Z37: 4 | AA37: 5 | AB37: TOT
A38: =A28 -> OS | C38: =C28 -> 0 | D38: =D28 -> 2000 | E38: =E28 -> 1 | F38: =F28 -> 0.2 | G38: =G28 -> socket | H38: =H28 -> socket | I38: =I28 -> 1 | J38: =$O$20 -> 6 | K38: =$P$20 -> 12 | L38: =$Q$20 -> 240 | O38: =_xlfn.XLOOKUP($H38,$J$27:$L$27,$J38:$L38) -> 12 | P38: socket | Q38: =I38*O38 -> 12 | R38: =$Q38*$C38*(1-$F38) -> 0 | W38: =IF(W$18<$E38,0,$Q38*$D38)*(1-$F38) -> 19200 | X38: =IF(X$18<$E38,0,$Q38*$D38)*(1-$F38) -> 19200 | Y38: =IF(Y$18<$E38,0,$Q38*$D38)*(1-$F38) -> 19200 | Z38: =IF(Z$18<$E38,0,$Q38*$D38)*(1-$F38) -> 19200 | AA38: =IF(AA$18<$E38,0,$Q38*$D38)*(1-$F38) -> 19200 | AB38: =SUM(R38:AA38) -> 96000
A39: =A29 -> VM | C39: =C29 -> 5000 | D39: =D29 -> 1000 | E39: =E29 -> 2 | F39: =F29 -> 0.2 | G39: =G29 -> socket | H39: =H29 -> socket | I39: =I29 -> 1 | J39: =J38 -> 6 | K39: =K38 -> 12 | L39: =L38 -> 240 | O39: =_xlfn.XLOOKUP($H39,$J$27:$L$27,$J39:$L39) -> 12 | P39: socket | Q39: =I39*O39 -> 12 | R39: =$Q39*$C39*(1-$F39) -> 48000 | W39: =IF(W$18<$E39,0,$Q39*$D39)*(1-$F39) -> 0 | X39: =IF(X$18<$E39,0,$Q39*$D39)*(1-$F39) -> 9600 | Y39: =IF(Y$18<$E39,0,$Q39*$D39)*(1-$F39) -> 9600 | Z39: =IF(Z$18<$E39,0,$Q39*$D39)*(1-$F39) -> 9600 | AA39: =IF(AA$18<$E39,0,$Q39*$D39)*(1-$F39) -> 9600 | AB39: =SUM(R39:AA39) -> 86400
A40: =A30 -> Application Server | C40: =C30 -> 46.82 | D40: =D30 -> 9.36 | E40: =E30 -> 2 | F40: =F30 -> 0.75 | G40: =G30 -> PVU | H40: =H30 -> core | I40: =I30 -> 70 | J40: =J39 -> 6 | K40: =K39 -> 12 | L40: =L39 -> 240 | O40: =_xlfn.XLOOKUP($H40,$J$27:$L$27,$J40:$L40) -> 240 | P40: PVU | Q40: =I40*O40 -> 16800 | R40: =$Q40*$C40*(1-$F40) -> 196644 | W40: =IF(W$18<$E40,0,$Q40*$D40)*(1-$F40) -> 0 | X40: =IF(X$18<$E40,0,$Q40*$D40)*(1-$F40) -> 39312 | Y40: =IF(Y$18<$E40,0,$Q40*$D40)*(1-$F40) -> 39312 | Z40: =IF(Z$18<$E40,0,$Q40*$D40)*(1-$F40) -> 39312 | AA40: =IF(AA$18<$E40,0,$Q40*$D40)*(1-$F40) -> 39312 | AB40: =SUM(R40:AA40) -> 353892
A41: =A31 -> DB | C41: =C31 -> 0 | D41: =D31 -> 8500 | E41: =E31 -> 1 | F41: =F31 -> 0 | G41: =G31 -> server | H41: =H31 -> server | I41: =I31 -> 1 | J41: =J40 -> 6 | K41: =K40 -> 12 | L41: =L40 -> 240 | O41: =_xlfn.XLOOKUP($H41,$J$27:$L$27,$J41:$L41) -> 6 | P41: core | Q41: =I41*O41 -> 6 | R41: =$Q41*$C41*(1-$F41) -> 0 | W41: =IF(W$18<$E41,0,$Q41*$D41)*(1-$F41) -> 51000 | X41: =IF(X$18<$E41,0,$Q41*$D41)*(1-$F41) -> 51000 | Y41: =IF(Y$18<$E41,0,$Q41*$D41)*(1-$F41) -> 51000 | Z41: =IF(Z$18<$E41,0,$Q41*$D41)*(1-$F41) -> 51000 | AA41: =IF(AA$18<$E41,0,$Q41*$D41)*(1-$F41) -> 51000 | AB41: =SUM(R41:AA41) -> 255000
A42: =A32 -> Data Replication Tools | C42: =C32 -> 0 | D42: =D32 -> 3000 | E42: =E32 -> 1 | F42: =F32 -> 0.75 | G42: =G32 -> core | H42: =H32 -> core | I42: =I32 -> 0.5 | J42: =J41 -> 6 | K42: =K41 -> 12 | L42: =L41 -> 240 | O42: =_xlfn.XLOOKUP($H42,$J$27:$L$27,$J42:$L42) -> 240 | P42: core | Q42: =I42*O42 -> 120 | R42: =$Q42*$C42*(1-$F42) -> 0 | W42: =IF(W$18<$E42,0,$Q42*$D42)*(1-$F42) -> 90000 | X42: =IF(X$18<$E42,0,$Q42*$D42)*(1-$F42) -> 90000 | Y42: =IF(Y$18<$E42,0,$Q42*$D42)*(1-$F42) -> 90000 | Z42: =IF(Z$18<$E42,0,$Q42*$D42)*(1-$F42) -> 90000 | AA42: =IF(AA$18<$E42,0,$Q42*$D42)*(1-$F42) -> 90000 | AB42: =SUM(R42:AA42) -> 450000
A43: =A33 -> Monitoring Tools | C43: =C33 -> 5000 | D43: =D33 -> 1000 | E43: =E33 -> 2 | F43: =F33 -> 0.4 | G43: =G33 -> server | H43: =H33 -> server | I43: =I33 -> 1 | J43: =J42 -> 6 | K43: =K42 -> 12 | L43: =L42 -> 240 | O43: =_xlfn.XLOOKUP($H43,$J$27:$L$27,$J43:$L43) -> 6 | P43: server | Q43: =I43*O43 -> 6 | R43: =$Q43*$C43*(1-$F43) -> 18000 | W43: =IF(W$18<$E43,0,$Q43*$D43)*(1-$F43) -> 0 | X43: =IF(X$18<$E43,0,$Q43*$D43)*(1-$F43) -> 3600 | Y43: =IF(Y$18<$E43,0,$Q43*$D43)*(1-$F43) -> 3600 | Z43: =IF(Z$18<$E43,0,$Q43*$D43)*(1-$F43) -> 3600 | AA43: =IF(AA$18<$E43,0,$Q43*$D43)*(1-$F43) -> 3600 | AB43: =SUM(R43:AA43) -> 32400
A44: =A34 -> Security Tools | C44: =C34 -> 5000 | D44: =D34 -> 1000 | E44: =E34 -> 2 | F44: =F34 -> 0.4 | G44: =G34 -> server | H44: =H34 -> server | I44: =I34 -> 1 | J44: =J43 -> 6 | K44: =K43 -> 12 | L44: =L43 -> 240 | O44: =_xlfn.XLOOKUP($H44,$J$27:$L$27,$J44:$L44) -> 6 | P44: server | Q44: =I44*O44 -> 6 | R44: =$Q44*$C44*(1-$F44) -> 18000 | W44: =IF(W$18<$E44,0,$Q44*$D44)*(1-$F44) -> 0 | X44: =IF(X$18<$E44,0,$Q44*$D44)*(1-$F44) -> 3600 | Y44: =IF(Y$18<$E44,0,$Q44*$D44)*(1-$F44) -> 3600 | Z44: =IF(Z$18<$E44,0,$Q44*$D44)*(1-$F44) -> 3600 | AA44: =IF(AA$18<$E44,0,$Q44*$D44)*(1-$F44) -> 3600 | AB44: =SUM(R44:AA44) -> 32400
Q45: DEV | R45: =SUM(R38:R44) -> 280644 | S45: =SUM(S38:S44) -> 0 | T45: =SUM(T38:T44) -> 0 | U45: =SUM(U38:U44) -> 0 | V45: =SUM(V38:V44) -> 0 | W45: =SUM(W38:W44) -> 160200 | X45: =SUM(X38:X44) -> 216312 | Y45: =SUM(Y38:Y44) -> 216312 | ... AB45: =SUM(AB38:AB44) -> 1306092
A47: Test | C47: Acquisition/ Capital Cost | D47: Maintenance/ Operating Cost | E47: =E37 -> Starting Year of yearly charges | F47: Discount % | G47: Unit of Measure | H47: Measured by | I47: conversion factor | J47: server | K47: socket | L47: core | O47: count | P47: Unit of Measure | Q47: Units | R47: 1 | S47: 2 | T47: 3 | U47: 4 | V47: 5 | W47: 1 | X47: 2 | Y47: 3 | Z47: 4 | AA47: 5 | AB47: TOT
A48: =A28 -> OS | C48: =C28 -> 0 | D48: =D28 -> 2000 | E48: =E28 -> 1 | F48: =F28 -> 0.2 | G48: =G38 -> socket | H48: =H38 -> socket | I48: =I38 -> 1 | J48: =$O$21 -> 6 | K48: =$P$21 -> 12 | L48: =$Q$21 -> 240 | O48: =_xlfn.XLOOKUP($H48,$J$27:$L$27,$J48:$L48) -> 12 | P48: socket | Q48: =I48*O48 -> 12 | R48: =$Q48*$C48*(1-$F48) -> 0 | W48: =IF(W$18<$E48,0,$Q48*$D48)*(1-$F48) -> 19200 | X48: =IF(X$18<$E48,0,$Q48*$D48)*(1-$F48) -> 19200 | Y48: =IF(Y$18<$E48,0,$Q48*$D48)*(1-$F48) -> 19200 | Z48: =IF(Z$18<$E48,0,$Q48*$D48)*(1-$F48) -> 19200 | AA48: =IF(AA$18<$E48,0,$Q48*$D48)*(1-$F48) -> 19200 | AB48: =SUM(R48:AA48) -> 96000
A49: =A29 -> VM | C49: =C29 -> 5000 | D49: =D29 -> 1000 | E49: =E29 -> 2 | F49: =F29 -> 0.2 | G49: =G39 -> socket | H49: =H39 -> socket | I49: =I39 -> 1 | J49: =J48 -> 6 | K49: =K48 -> 12 | L49: =L48 -> 240 | O49: =_xlfn.XLOOKUP($H49,$J$27:$L$27,$J49:$L49) -> 12 | P49: socket | Q49: =I49*O49 -> 12 | R49: =$Q49*$C49*(1-$F49) -> 48000 | W49: =IF(W$18<$E49,0,$Q49*$D49)*(1-$F49) -> 0 | X49: =IF(X$18<$E49,0,$Q49*$D49)*(1-$F49) -> 9600 | Y49: =IF(Y$18<$E49,0,$Q49*$D49)*(1-$F49) -> 9600 | Z49: =IF(Z$18<$E49,0,$Q49*$D49)*(1-$F49) -> 9600 | AA49: =IF(AA$18<$E49,0,$Q49*$D49)*(1-$F49) -> 9600 | AB49: =SUM(R49:AA49) -> 86400
A50: =A30 -> Application Server | C50: =C30 -> 46.82 | D50: =D30 -> 9.36 | E50: =E30 -> 2 | F50: =F30 -> 0.75 | G50: =G40 -> PVU | H50: =H40 -> core | I50: =I40 -> 70 | J50: =J49 -> 6 | K50: =K49 -> 12 | L50: =L49 -> 240 | O50: =_xlfn.XLOOKUP($H50,$J$27:$L$27,$J50:$L50) -> 240 | P50: PVU | Q50: =I50*O50 -> 16800 | R50: =$Q50*$C50*(1-$F50) -> 196644 | W50: =IF(W$18<$E50,0,$Q50*$D50)*(1-$F50) -> 0 | X50: =IF(X$18<$E50,0,$Q50*$D50)*(1-$F50) -> 39312 | Y50: =IF(Y$18<$E50,0,$Q50*$D50)*(1-$F50) -> 39312 | Z50: =IF(Z$18<$E50,0,$Q50*$D50)*(1-$F50) -> 39312 | AA50: =IF(AA$18<$E50,0,$Q50*$D50)*(1-$F50) -> 39312 | AB50: =SUM(R50:AA50) -> 353892
A51: =A31 -> DB | C51: =C31 -> 0 | D51: =D31 -> 8500 | E51: =E31 -> 1 | F51: =F31 -> 0 | G51: =G41 -> server | H51: =H41 -> server | I51: =I41 -> 1 | J51: =J50 -> 6 | K51: =K50 -> 12 | L51: =L50 -> 240 | O51: =_xlfn.XLOOKUP($H51,$J$27:$L$27,$J51:$L51) -> 6 | P51: core | Q51: =I51*O51 -> 6 | R51: =$Q51*$C51*(1-$F51) -> 0 | W51: =IF(W$18<$E51,0,$Q51*$D51)*(1-$F51) -> 51000 | X51: =IF(X$18<$E51,0,$Q51*$D51)*(1-$F51) -> 51000 | Y51: =IF(Y$18<$E51,0,$Q51*$D51)*(1-$F51) -> 51000 | Z51: =IF(Z$18<$E51,0,$Q51*$D51)*(1-$F51) -> 51000 | AA51: =IF(AA$18<$E51,0,$Q51*$D51)*(1-$F51) -> 51000 | AB51: =SUM(R51:AA51) -> 255000
A52: =A32 -> Data Replication Tools | C52: =C32 -> 0 | D52: =D32 -> 3000 | E52: =E32 -> 1 | F52: =F32 -> 0.75 | G52: =G42 -> core | H52: =H42 -> core | I52: =I42 -> 0.5 | J52: =J51 -> 6 | K52: =K51 -> 12 | L52: =L51 -> 240 | O52: =_xlfn.XLOOKUP($H52,$J$27:$L$27,$J52:$L52) -> 240 | P52: core | Q52: =I52*O52 -> 120 | R52: =$Q52*$C52*(1-$F52) -> 0 | W52: =IF(W$18<$E52,0,$Q52*$D52)*(1-$F52) -> 90000 | X52: =IF(X$18<$E52,0,$Q52*$D52)*(1-$F52) -> 90000 | Y52: =IF(Y$18<$E52,0,$Q52*$D52)*(1-$F52) -> 90000 | Z52: =IF(Z$18<$E52,0,$Q52*$D52)*(1-$F52) -> 90000 | AA52: =IF(AA$18<$E52,0,$Q52*$D52)*(1-$F52) -> 90000 | AB52: =SUM(R52:AA52) -> 450000
A53: =A33 -> Monitoring Tools | C53: =C33 -> 5000 | D53: =D33 -> 1000 | E53: =E33 -> 2 | F53: =F33 -> 0.4 | G53: =G43 -> server | H53: =H43 -> server | I53: =I43 -> 1 | J53: =J52 -> 6 | K53: =K52 -> 12 | L53: =L52 -> 240 | O53: =_xlfn.XLOOKUP($H53,$J$27:$L$27,$J53:$L53) -> 6 | P53: server | Q53: =I53*O53 -> 6 | R53: =$Q53*$C53*(1-$F53) -> 18000 | W53: =IF(W$18<$E53,0,$Q53*$D53)*(1-$F53) -> 0 | X53: =IF(X$18<$E53,0,$Q53*$D53)*(1-$F53) -> 3600 | Y53: =IF(Y$18<$E53,0,$Q53*$D53)*(1-$F53) -> 3600 | Z53: =IF(Z$18<$E53,0,$Q53*$D53)*(1-$F53) -> 3600 | AA53: =IF(AA$18<$E53,0,$Q53*$D53)*(1-$F53) -> 3600 | AB53: =SUM(R53:AA53) -> 32400
A54: =A34 -> Security Tools | C54: =C34 -> 5000 | D54: =D34 -> 1000 | E54: =E34 -> 2 | F54: =F34 -> 0.4 | G54: =G44 -> server | H54: =H44 -> server | I54: =I44 -> 1 | J54: =J53 -> 6 | K54: =K53 -> 12 | L54: =L53 -> 240 | O54: =_xlfn.XLOOKUP($H54,$J$27:$L$27,$J54:$L54) -> 6 | P54: server | Q54: =I54*O54 -> 6 | R54: =$Q54*$C54*(1-$F54) -> 18000 | W54: =IF(W$18<$E54,0,$Q54*$D54)*(1-$F54) -> 0 | X54: =IF(X$18<$E54,0,$Q54*$D54)*(1-$F54) -> 3600 | Y54: =IF(Y$18<$E54,0,$Q54*$D54)*(1-$F54) -> 3600 | Z54: =IF(Z$18<$E54,0,$Q54*$D54)*(1-$F54) -> 3600 | AA54: =IF(AA$18<$E54,0,$Q54*$D54)*(1-$F54) -> 3600 | AB54: =SUM(R54:AA54) -> 32400
Q55: Test | R55: =SUM(R48:R54) -> 280644 | S55: =SUM(S48:S54) -> 0 | T55: =SUM(T48:T54) -> 0 | U55: =SUM(U48:U54) -> 0 | V55: =SUM(V48:V54) -> 0 | W55: =SUM(W48:W54) -> 160200 | X55: =SUM(X48:X54) -> 216312 | Y55: =SUM(Y48:Y54) -> 216312 | ... AB55: =SUM(AB48:AB54) -> 1306092
A57: Pre Prod / QA | C57: Acquisition/ Capital Cost | D57: Maintenance/ Operating Cost | E57: =E47 -> Starting Year of yearly charges | F57: Discount % | G57: Unit of Measure | H57: Measured by | I57: conversion factor | J57: server | K57: socket | L57: core | O57: count | P57: Unit of Measure | Q57: Units | R57: 1 | S57: 2 | T57: 3 | U57: 4 | V57: 5 | W57: 1 | X57: 2 | Y57: 3 | Z57: 4 | AA57: 5 | AB57: TOT
A58: =A28 -> OS | C58: =C28 -> 0 | D58: =D28 -> 2000 | E58: =E28 -> 1 | F58: =F28 -> 0.2 | G58: =G48 -> socket | H58: =H48 -> socket | I58: =I48 -> 1 | J58: =$O$22 -> 12 | K58: =$P$22 -> 24 | L58: =$Q$22 -> 480 | O58: =_xlfn.XLOOKUP($H58,$J$27:$L$27,$J58:$L58) -> 24 | P58: socket | Q58: =I58*O58 -> 24 | R58: =$Q58*$C58*(1-$F58) -> 0 | W58: =IF(W$18<$E58,0,$Q58*$D58)*(1-$F58) -> 38400 | X58: =IF(X$18<$E58,0,$Q58*$D58)*(1-$F58) -> 38400 | Y58: =IF(Y$18<$E58,0,$Q58*$D58)*(1-$F58) -> 38400 | Z58: =IF(Z$18<$E58,0,$Q58*$D58)*(1-$F58) -> 38400 | AA58: =IF(AA$18<$E58,0,$Q58*$D58)*(1-$F58) -> 38400 | AB58: =SUM(R58:AA58) -> 192000
A59: =A29 -> VM | C59: =C29 -> 5000 | D59: =D29 -> 1000 | E59: =E29 -> 2 | F59: =F29 -> 0.2 | G59: =G49 -> socket | H59: =H49 -> socket | I59: =I49 -> 1 | J59: =J58 -> 12 | K59: =K58 -> 24 | L59: =L58 -> 480 | O59: =_xlfn.XLOOKUP($H59,$J$27:$L$27,$J59:$L59) -> 24 | P59: socket | Q59: =I59*O59 -> 24 | R59: =$Q59*$C59*(1-$F59) -> 96000 | W59: =IF(W$18<$E59,0,$Q59*$D59)*(1-$F59) -> 0 | X59: =IF(X$18<$E59,0,$Q59*$D59)*(1-$F59) -> 19200 | Y59: =IF(Y$18<$E59,0,$Q59*$D59)*(1-$F59) -> 19200 | Z59: =IF(Z$18<$E59,0,$Q59*$D59)*(1-$F59) -> 19200 | AA59: =IF(AA$18<$E59,0,$Q59*$D59)*(1-$F59) -> 19200 | AB59: =SUM(R59:AA59) -> 172800
A60: =A30 -> Application Server | C60: =C30 -> 46.82 | D60: =D30 -> 9.36 | E60: =E30 -> 2 | F60: =F30 -> 0.75 | G60: =G50 -> PVU | H60: =H50 -> core | I60: =I50 -> 70 | J60: =J59 -> 12 | K60: =K59 -> 24 | L60: =L59 -> 480 | O60: =_xlfn.XLOOKUP($H60,$J$27:$L$27,$J60:$L60) -> 480 | P60: PVU | Q60: =I60*O60 -> 33600 | R60: =$Q60*$C60*(1-$F60) -> 393288 | W60: =IF(W$18<$E60,0,$Q60*$D60)*(1-$F60) -> 0 | X60: =IF(X$18<$E60,0,$Q60*$D60)*(1-$F60) -> 78624 | Y60: =IF(Y$18<$E60,0,$Q60*$D60)*(1-$F60) -> 78624 | Z60: =IF(Z$18<$E60,0,$Q60*$D60)*(1-$F60) -> 78624 | AA60: =IF(AA$18<$E60,0,$Q60*$D60)*(1-$F60) -> 78624 | AB60: =SUM(R60:AA60) -> 707784
A61: =A31 -> DB | C61: =C31 -> 0 | D61: =D31 -> 8500 | E61: =E31 -> 1 | F61: =F31 -> 0 | G61: =G51 -> server | H61: =H51 -> server | I61: =I51 -> 1 | J61: =J60 -> 12 | K61: =K60 -> 24 | L61: =L60 -> 480 | O61: =_xlfn.XLOOKUP($H61,$J$27:$L$27,$J61:$L61) -> 12 | P61: core | Q61: =I61*O61 -> 12 | R61: =$Q61*$C61*(1-$F61) -> 0 | W61: =IF(W$18<$E61,0,$Q61*$D61)*(1-$F61) -> 102000 | X61: =IF(X$18<$E61,0,$Q61*$D61)*(1-$F61) -> 102000 | Y61: =IF(Y$18<$E61,0,$Q61*$D61)*(1-$F61) -> 102000 | Z61: =IF(Z$18<$E61,0,$Q61*$D61)*(1-$F61) -> 102000 | AA61: =IF(AA$18<$E61,0,$Q61*$D61)*(1-$F61) -> 102000 | AB61: =SUM(R61:AA61) -> 510000
A62: =A32 -> Data Replication Tools | C62: =C32 -> 0 | D62: =D32 -> 3000 | E62: =E32 -> 1 | F62: =F32 -> 0.75 | G62: =G52 -> core | H62: =H52 -> core | I62: =I52 -> 0.5 | J62: =J61 -> 12 | K62: =K61 -> 24 | L62: =L61 -> 480 | O62: =_xlfn.XLOOKUP($H62,$J$27:$L$27,$J62:$L62) -> 480 | P62: core | Q62: =I62*O62 -> 240 | R62: =$Q62*$C62*(1-$F62) -> 0 | W62: =IF(W$18<$E62,0,$Q62*$D62)*(1-$F62) -> 180000 | X62: =IF(X$18<$E62,0,$Q62*$D62)*(1-$F62) -> 180000 | Y62: =IF(Y$18<$E62,0,$Q62*$D62)*(1-$F62) -> 180000 | Z62: =IF(Z$18<$E62,0,$Q62*$D62)*(1-$F62) -> 180000 | AA62: =IF(AA$18<$E62,0,$Q62*$D62)*(1-$F62) -> 180000 | AB62: =SUM(R62:AA62) -> 900000
A63: =A33 -> Monitoring Tools | C63: =C33 -> 5000 | D63: =D33 -> 1000 | E63: =E33 -> 2 | F63: =F33 -> 0.4 | G63: =G53 -> server | H63: =H53 -> server | I63: =I53 -> 1 | J63: =J62 -> 12 | K63: =K62 -> 24 | L63: =L62 -> 480 | O63: =_xlfn.XLOOKUP($H63,$J$27:$L$27,$J63:$L63) -> 12 | P63: server | Q63: =I63*O63 -> 12 | R63: =$Q63*$C63*(1-$F63) -> 36000 | W63: =IF(W$18<$E63,0,$Q63*$D63)*(1-$F63) -> 0 | X63: =IF(X$18<$E63,0,$Q63*$D63)*(1-$F63) -> 7200 | Y63: =IF(Y$18<$E63,0,$Q63*$D63)*(1-$F63) -> 7200 | Z63: =IF(Z$18<$E63,0,$Q63*$D63)*(1-$F63) -> 7200 | AA63: =IF(AA$18<$E63,0,$Q63*$D63)*(1-$F63) -> 7200 | AB63: =SUM(R63:AA63) -> 64800
A64: =A34 -> Security Tools | C64: =C34 -> 5000 | D64: =D34 -> 1000 | E64: =E34 -> 2 | F64: =F34 -> 0.4 | G64: =G54 -> server | H64: =H54 -> server | I64: =I54 -> 1 | J64: =J63 -> 12 | K64: =K63 -> 24 | L64: =L63 -> 480 | O64: =_xlfn.XLOOKUP($H64,$J$27:$L$27,$J64:$L64) -> 12 | P64: server | Q64: =I64*O64 -> 12 | R64: =$Q64*$C64*(1-$F64) -> 36000 | W64: =IF(W$18<$E64,0,$Q64*$D64)*(1-$F64) -> 0 | X64: =IF(X$18<$E64,0,$Q64*$D64)*(1-$F64) -> 7200 | Y64: =IF(Y$18<$E64,0,$Q64*$D64)*(1-$F64) -> 7200 | Z64: =IF(Z$18<$E64,0,$Q64*$D64)*(1-$F64) -> 7200 | AA64: =IF(AA$18<$E64,0,$Q64*$D64)*(1-$F64) -> 7200 | AB64: =SUM(R64:AA64) -> 64800
Q65: Pre Prod /QA | R65: =SUM(R58:R64) -> 561288 | S65: =SUM(S58:S64) -> 0 | T65: =SUM(T58:T64) -> 0 | U65: =SUM(U58:U64) -> 0 | V65: =SUM(V58:V64) -> 0 | W65: =SUM(W58:W64) -> 320400 | X65: =SUM(X58:X64) -> 432624 | Y65: =SUM(Y58:Y64) -> 432624 | ... AB65: =SUM(AB58:AB64) -> 2612184
A67: DR | C67: Acquisition/ Capital Cost | D67: Maintenance/ Operating Cost | E67: =E57 -> Starting Year of yearly charges | F67: Discount % | G67: Unit of Measure | H67: Measured by | I67: conversion factor | J67: server | K67: socket | L67: core | O67: count | P67: Unit of Measure | Q67: Units | R67: 1 | S67: 2 | T67: 3 | U67: 4 | V67: 5 | W67: 1 | X67: 2 | Y67: 3 | Z67: 4 | AA67: 5 | AB67: TOT
A68: =A28 -> OS | C68: =C28 -> 0 | D68: =D28 -> 2000 | E68: =E28 -> 1 | F68: =F28 -> 0.2 | G68: =G58 -> socket | H68: =H58 -> socket | I68: =I58 -> 1 | J68: =$O$23 -> 24 | K68: =$P$23 -> 48 | L68: =$Q$23 -> 960 | O68: =_xlfn.XLOOKUP($H68,$J$27:$L$27,$J68:$L68) -> 48 | P68: socket | Q68: =I68*O68 -> 48 | R68: =$Q68*$C68*(1-$F68) -> 0 | W68: =IF(W$18<$E68,0,$Q68*$D68)*(1-$F68) -> 76800 | X68: =IF(X$18<$E68,0,$Q68*$D68)*(1-$F68) -> 76800 | Y68: =IF(Y$18<$E68,0,$Q68*$D68)*(1-$F68) -> 76800 | Z68: =IF(Z$18<$E68,0,$Q68*$D68)*(1-$F68) -> 76800 | AA68: =IF(AA$18<$E68,0,$Q68*$D68)*(1-$F68) -> 76800 | AB68: =SUM(R68:AA68) -> 384000
A69: =A29 -> VM | C69: =C29 -> 5000 | D69: =D29 -> 1000 | E69: =E29 -> 2 | F69: =F29 -> 0.2 | G69: =G59 -> socket | H69: =H59 -> socket | I69: =I59 -> 1 | J69: =J68 -> 24 | K69: =K68 -> 48 | L69: =L68 -> 960 | O69: =_xlfn.XLOOKUP($H69,$J$27:$L$27,$J69:$L69) -> 48 | P69: socket | Q69: =I69*O69 -> 48 | R69: =$Q69*$C69*(1-$F69) -> 192000 | W69: =IF(W$18<$E69,0,$Q69*$D69)*(1-$F69) -> 0 | X69: =IF(X$18<$E69,0,$Q69*$D69)*(1-$F69) -> 38400 | Y69: =IF(Y$18<$E69,0,$Q69*$D69)*(1-$F69) -> 38400 | Z69: =IF(Z$18<$E69,0,$Q69*$D69)*(1-$F69) -> 38400 | AA69: =IF(AA$18<$E69,0,$Q69*$D69)*(1-$F69) -> 38400 | AB69: =SUM(R69:AA69) -> 345600
A70: =A30 -> Application Server | C70: =C30 -> 46.82 | D70: =D30 -> 9.36 | E70: =E30 -> 2 | F70: =F30 -> 0.75 | G70: =G60 -> PVU | H70: =H60 -> core | I70: =I60 -> 70 | J70: =J69 -> 24 | K70: =K69 -> 48 | L70: =L69 -> 960 | O70: =_xlfn.XLOOKUP($H70,$J$27:$L$27,$J70:$L70) -> 960 | P70: PVU | Q70: =I70*O70 -> 67200 | R70: =$Q70*$C70*(1-$F70) -> 786576 | W70: =IF(W$18<$E70,0,$Q70*$D70)*(1-$F70) -> 0 | X70: =IF(X$18<$E70,0,$Q70*$D70)*(1-$F70) -> 157248 | Y70: =IF(Y$18<$E70,0,$Q70*$D70)*(1-$F70) -> 157248 | Z70: =IF(Z$18<$E70,0,$Q70*$D70)*(1-$F70) -> 157248 | AA70: =IF(AA$18<$E70,0,$Q70*$D70)*(1-$F70) -> 157248 | AB70: =SUM(R70:AA70) -> 1415568
A71: =A31 -> DB | C71: =C31 -> 0 | D71: =D31 -> 8500 | E71: =E31 -> 1 | F71: =F31 -> 0 | G71: =G61 -> server | H71: =H61 -> server | I71: =I61 -> 1 | J71: =J70 -> 24 | K71: =K70 -> 48 | L71: =L70 -> 960 | O71: =_xlfn.XLOOKUP($H71,$J$27:$L$27,$J71:$L71) -> 24 | P71: core | Q71: =I71*O71 -> 24 | R71: =$Q71*$C71*(1-$F71) -> 0 | W71: =IF(W$18<$E71,0,$Q71*$D71)*(1-$F71) -> 204000 | X71: =IF(X$18<$E71,0,$Q71*$D71)*(1-$F71) -> 204000 | Y71: =IF(Y$18<$E71,0,$Q71*$D71)*(1-$F71) -> 204000 | Z71: =IF(Z$18<$E71,0,$Q71*$D71)*(1-$F71) -> 204000 | AA71: =IF(AA$18<$E71,0,$Q71*$D71)*(1-$F71) -> 204000 | AB71: =SUM(R71:AA71) -> 1020000
A72: =A32 -> Data Replication Tools | C72: =C32 -> 0 | D72: =D32 -> 3000 | E72: =E32 -> 1 | F72: =F32 -> 0.75 | G72: =G62 -> core | H72: =H62 -> core | I72: =I62 -> 0.5 | J72: =J71 -> 24 | K72: =K71 -> 48 | L72: =L71 -> 960 | O72: =_xlfn.XLOOKUP($H72,$J$27:$L$27,$J72:$L72) -> 960 | P72: core | Q72: =I72*O72 -> 480 | R72: =$Q72*$C72*(1-$F72) -> 0 | W72: =IF(W$18<$E72,0,$Q72*$D72)*(1-$F72) -> 360000 | X72: =IF(X$18<$E72,0,$Q72*$D72)*(1-$F72) -> 360000 | Y72: =IF(Y$18<$E72,0,$Q72*$D72)*(1-$F72) -> 360000 | Z72: =IF(Z$18<$E72,0,$Q72*$D72)*(1-$F72) -> 360000 | AA72: =IF(AA$18<$E72,0,$Q72*$D72)*(1-$F72) -> 360000 | AB72: =SUM(R72:AA72) -> 1800000
A73: =A33 -> Monitoring Tools | C73: =C33 -> 5000 | D73: =D33 -> 1000 | E73: =E33 -> 2 | F73: =F33 -> 0.4 | G73: =G63 -> server | H73: =H63 -> server | I73: =I63 -> 1 | J73: =J72 -> 24 | K73: =K72 -> 48 | L73: =L72 -> 960 | O73: =_xlfn.XLOOKUP($H73,$J$27:$L$27,$J73:$L73) -> 24 | P73: server | Q73: =I73*O73 -> 24 | R73: =$Q73*$C73*(1-$F73) -> 72000 | W73: =IF(W$18<$E73,0,$Q73*$D73)*(1-$F73) -> 0 | X73: =IF(X$18<$E73,0,$Q73*$D73)*(1-$F73) -> 14400 | Y73: =IF(Y$18<$E73,0,$Q73*$D73)*(1-$F73) -> 14400 | Z73: =IF(Z$18<$E73,0,$Q73*$D73)*(1-$F73) -> 14400 | AA73: =IF(AA$18<$E73,0,$Q73*$D73)*(1-$F73) -> 14400 | AB73: =SUM(R73:AA73) -> 129600
A74: =A34 -> Security Tools | C74: =C34 -> 5000 | D74: =D34 -> 1000 | E74: =E34 -> 2 | F74: =F34 -> 0.4 | G74: =G64 -> server | H74: =H64 -> server | I74: =I64 -> 1 | J74: =J73 -> 24 | K74: =K73 -> 48 | L74: =L73 -> 960 | O74: =_xlfn.XLOOKUP($H74,$J$27:$L$27,$J74:$L74) -> 24 | P74: server | Q74: =I74*O74 -> 24 | R74: =$Q74*$C74*(1-$F74) -> 72000 | W74: =IF(W$18<$E74,0,$Q74*$D74)*(1-$F74) -> 0 | X74: =IF(X$18<$E74,0,$Q74*$D74)*(1-$F74) -> 14400 | Y74: =IF(Y$18<$E74,0,$Q74*$D74)*(1-$F74) -> 14400 | Z74: =IF(Z$18<$E74,0,$Q74*$D74)*(1-$F74) -> 14400 | AA74: =IF(AA$18<$E74,0,$Q74*$D74)*(1-$F74) -> 14400 | AB74: =SUM(R74:AA74) -> 129600
Q75: DR | R75: =SUM(R68:R74) -> 1122576 | S75: =SUM(S68:S74) -> 0 | T75: =SUM(T68:T74) -> 0 | U75: =SUM(U68:U74) -> 0 | V75: =SUM(V68:V74) -> 0 | W75: =SUM(W68:W74) -> 640800 | X75: =SUM(X68:X74) -> 865248 | Y75: =SUM(Y68:Y74) -> 865248 | ... AB75: =SUM(AB68:AB74) -> 5224368
O77: Software Stack TOTALS | R77: =R35+R45+R55+R65+R75 -> 2806440 | S77: =S35+S45+S55+S65+S75 -> 0 | T77: =T35+T45+T55+T65+T75 -> 0 | U77: =U35+U45+U55+U65+U75 -> 0 | V77: =V35+V45+V55+V65+V75 -> 0 | W77: =W35+W45+W55+W65+W75 -> 1602000 | X77: =X35+X45+X55+X65+X75 -> 2163120 | Y77: =Y35+Y45+Y55+Y65+Y75 -> 2163120 | ... AB77: =AB35+AB45+AB55+AB65+AB75 -> 13060920 | AC77: TOT
A79: People
A80: People | O80: # of Server | P80: FTE Require | R80: 1 | S80: 2 | T80: 3 | U80: 4 | V80: 5 | W80: 1 | X80: 2 | Y80: 3 | Z80: 4 | AA80: 5 | AB80: TOT
A81: # of Servers covered by 1 FTE for IT Operations considering QoS | D81: 30 | E81: This is for patches, upgrade, backup, Crit Sit or Disaster recovery personnels, etc | N81: Prod | O81: =$O$19 -> 12 | P81: =$O81/$D$81 -> 0.4 | W81: =$D$82*$P81 -> 40000 | X81: =$D$82*$P81 -> 40000 | Y81: =$D$82*$P81 -> 40000 | Z81: =$D$82*$P81 -> 40000 | AA81: =$D$82*$P81 -> 40000 | AB81: =SUM(R81:AA81) -> 200000 | AC81: Prod
A82: Avg yearly Fully loaded cost of IT Staff | D82: 100000 | N82: Dev | O82: =$O$20 -> 6 | P82: =$O82/$D$81 -> 0.2 | W82: =$D$82*$P82 -> 20000 | X82: =$D$82*$P82 -> 20000 | Y82: =$D$82*$P82 -> 20000 | Z82: =$D$82*$P82 -> 20000 | AA82: =$D$82*$P82 -> 20000 | AB82: =SUM(R82:AA82) -> 100000 | AC82: Dev
N83: Test | O83: =$O$21 -> 6 | P83: =$O83/$D$81 -> 0.2 | W83: =$D$82*$P83 -> 20000 | X83: =$D$82*$P83 -> 20000 | Y83: =$D$82*$P83 -> 20000 | Z83: =$D$82*$P83 -> 20000 | AA83: =$D$82*$P83 -> 20000 | AB83: =SUM(R83:AA83) -> 100000 | AC83: Test
N84: QA | O84: =$O$22 -> 12 | P84: =$O84/$D$81 -> 0.4 | W84: =$D$82*$P84 -> 40000 | X84: =$D$82*$P84 -> 40000 | Y84: =$D$82*$P84 -> 40000 | Z84: =$D$82*$P84 -> 40000 | AA84: =$D$82*$P84 -> 40000 | AB84: =SUM(R84:AA84) -> 200000 | AC84: QA
N85: DR | O85: =$O$23 -> 24 | P85: =$O85/$D$81 -> 0.8 | W85: =$D$82*$P85 -> 80000 | X85: =$D$82*$P85 -> 80000 | Y85: =$D$82*$P85 -> 80000 | Z85: =$D$82*$P85 -> 80000 | AA85: =$D$82*$P85 -> 80000 | AB85: =SUM(R85:AA85) -> 400000 | AC85: DR
O86: TOT FTE required | P86: =SUM(P81:P85) -> 2 | R86: =SUM(R81:R85) -> 0 | S86: =SUM(S81:S85) -> 0 | T86: =SUM(T81:T85) -> 0 | U86: =SUM(U81:U85) -> 0 | V86: =SUM(V81:V85) -> 0 | W86: =SUM(W81:W85) -> 200000 | X86: =SUM(X81:X85) -> 200000 | Y86: =SUM(Y81:Y85) -> 200000 | ... AB86: =SUM(AB81:AB85) -> 1000000 | AC86: TOT
A88: Network
A89: Network | P89: # of Server | R89: 1 | S89: 2 | T89: 3 | U89: 4 | V89: 5 | W89: 1 | X89: 2 | Y89: 3 | Z89: 4 | AA89: 5 | AB89: TOT
A90: Avg cost of Networking Infrastructure per Server | D90: 7000 | O90: Prod | P90: =$O$19 -> 12 | R90: =$P90*($D$90*(1-$D$91)) -> 58800 | W90: =IF(W$89>=$D$94,$P90*($D$93*(1-$D$91)),0) -> 0 | X90: =IF(X$89>=$D$94,$P90*($D$93*(1-$D$91)),0) -> 5880 | Y90: =IF(Y$89>=$D$94,$P90*($D$93*(1-$D$91)),0) -> 5880 | Z90: =IF(Z$89>=$D$94,$P90*($D$93*(1-$D$91)),0) -> 5880 | AA90: =IF(AA$89>=$D$94,$P90*($D$93*(1-$D$91)),0) -> 5880 | AB90: =SUM(R90:AA90) -> 82320 | AC90: Prod
A91: Avg discount % | D91: 0.3 | O91: Dev | P91: =$O$20 -> 6 | R91: =$P91*($D$90*(1-$D$91)) -> 29400 | W91: =IF(W$89>=$D$94,$P91*($D$93*(1-$D$91)),0) -> 0 | X91: =IF(X$89>=$D$94,$P91*($D$93*(1-$D$91)),0) -> 2940 | Y91: =IF(Y$89>=$D$94,$P91*($D$93*(1-$D$91)),0) -> 2940 | Z91: =IF(Z$89>=$D$94,$P91*($D$93*(1-$D$91)),0) -> 2940 | AA91: =IF(AA$89>=$D$94,$P91*($D$93*(1-$D$91)),0) -> 2940 | AB91: =SUM(R91:AA91) -> 41160 | AC91: Dev
A92: Avg Maintenance/ Operating Cost (% of acq.) | D92: 0.1 | O92: Test | P92: =$O$21 -> 6 | R92: =$P92*($D$90*(1-$D$91)) -> 29400 | W92: =IF(W$89>=$D$94,$P92*($D$93*(1-$D$91)),0) -> 0 | X92: =IF(X$89>=$D$94,$P92*($D$93*(1-$D$91)),0) -> 2940 | Y92: =IF(Y$89>=$D$94,$P92*($D$93*(1-$D$91)),0) -> 2940 | Z92: =IF(Z$89>=$D$94,$P92*($D$93*(1-$D$91)),0) -> 2940 | AA92: =IF(AA$89>=$D$94,$P92*($D$93*(1-$D$91)),0) -> 2940 | AB92: =SUM(R92:AA92) -> 41160 | AC92: Test
A93: Avg Maintenance/ Operating Cost (Currency) | D93: =D90*D92 -> 700 | O93: QA | P93: =$O$22 -> 12 | R93: =$P93*($D$90*(1-$D$91)) -> 58800 | W93: =IF(W$89>=$D$94,$P93*($D$93*(1-$D$91)),0) -> 0 | X93: =IF(X$89>=$D$94,$P93*($D$93*(1-$D$91)),0) -> 5880 | Y93: =IF(Y$89>=$D$94,$P93*($D$93*(1-$D$91)),0) -> 5880 | Z93: =IF(Z$89>=$D$94,$P93*($D$93*(1-$D$91)),0) -> 5880 | AA93: =IF(AA$89>=$D$94,$P93*($D$93*(1-$D$91)),0) -> 5880 | AB93: =SUM(R93:AA93) -> 82320 | AC93: QA
A94: Starting Year of Maint | D94: 2 | O94: DR | P94: =$O$23 -> 24 | R94: =$P94*($D$90*(1-$D$91)) -> 117600 | W94: =IF(W$89>=$D$94,$P94*($D$93*(1-$D$91)),0) -> 0 | X94: =IF(X$89>=$D$94,$P94*($D$93*(1-$D$91)),0) -> 11760 | Y94: =IF(Y$89>=$D$94,$P94*($D$93*(1-$D$91)),0) -> 11760 | Z94: =IF(Z$89>=$D$94,$P94*($D$93*(1-$D$91)),0) -> 11760 | AA94: =IF(AA$89>=$D$94,$P94*($D$93*(1-$D$91)),0) -> 11760 | AB94: =SUM(R94:AA94) -> 164640 | AC94: DR
O95: TOT # of Servers | P95: =SUM(P90:P94) -> 60 | R95: =SUM(R90:R94) -> 294000 | S95: =SUM(S90:S94) -> 0 | T95: =SUM(T90:T94) -> 0 | U95: =SUM(U90:U94) -> 0 | V95: =SUM(V90:V94) -> 0 | W95: =SUM(W90:W94) -> 0 | X95: =SUM(X90:X94) -> 29400 | Y95: =SUM(Y90:Y94) -> 29400 | ... AB95: =SUM(AB90:AB94) -> 411600 | AC95: TOT
A97: Facilities
A98: Space | O98: # of Server | P98: # of Rack Cab | Q98: Avg. Footprint | R98: 1 | S98: 2 | T98: 3 | U98: 4 | V98: 5 | W98: 1 | X98: 2 | Y98: 3 | Z98: 4 | AA98: 5 | AB98: TOT
A99: Footprint of Server Rack Cabinet | C99: sq.m. | D99: 2.6 | N99: Prod | O99: =$O$19 -> 12 | P99: =$O99/$D$100 -> 0.8 | Q99: =ROUNDUP($P99*$D$99,0) -> 3 | W99: =$Q99*$D$101 -> 9204 | X99: =$Q99*$D$101 -> 9204 | Y99: =$Q99*$D$101 -> 9204 | Z99: =$Q99*$D$101 -> 9204 | AA99: =$Q99*$D$101 -> 9204 | AB99: =SUM(R99:AA99) -> 46020 | AC99: Prod
A100: # of "boxes" per Rack | D100: =$J$5 -> 15 | N100: Dev | O100: =$O$20 -> 6 | P100: =$O100/$D$100 -> 0.4 | Q100: =$P100*$D$99 -> 1.04 | W100: =$Q100*$D$101 -> 3190.72 | X100: =$Q100*$D$101 -> 3190.72 | Y100: =$Q100*$D$101 -> 3190.72 | Z100: =$Q100*$D$101 -> 3190.72 | AA100: =$Q100*$D$101 -> 3190.72 | AB100: =SUM(R100:AA100) -> 15953.6 | AC100: Dev
A101: Fully loaded cost of space per sq meter | C101: € | D101: =2600*Data!C1 -> 3068 | N101: Test | O101: =$O$21 -> 6 | P101: =$O101/$D$100 -> 0.4 | Q101: =$P101*$D$99 -> 1.04 | W101: =$Q101*$D$101 -> 3190.72 | X101: =$Q101*$D$101 -> 3190.72 | Y101: =$Q101*$D$101 -> 3190.72 | Z101: =$Q101*$D$101 -> 3190.72 | AA101: =$Q101*$D$101 -> 3190.72 | AB101: =SUM(R101:AA101) -> 15953.6 | AC101: Test
N102: QA | O102: =$O$22 -> 12 | P102: =$O102/$D$100 -> 0.8 | Q102: =$P102*$D$99 -> 2.08 | W102: =$Q102*$D$101 -> 6381.44 | X102: =$Q102*$D$101 -> 6381.44 | Y102: =$Q102*$D$101 -> 6381.44 | Z102: =$Q102*$D$101 -> 6381.44 | AA102: =$Q102*$D$101 -> 6381.44 | AB102: =SUM(R102:AA102) -> 31907.2 | AC102: QA
N103: DR | O103: =$O$23 -> 24 | P103: =$O103/$D$100 -> 1.6 | Q103: =ROUNDUP($P103*$D$99,0) -> 5 | W103: =$Q103*$D$101 -> 15340 | X103: =$Q103*$D$101 -> 15340 | Y103: =$Q103*$D$101 -> 15340 | Z103: =$Q103*$D$101 -> 15340 | AA103: =$Q103*$D$101 -> 15340 | AB103: =SUM(R103:AA103) -> 76700 | AC103: DR
O104: =SUM(O99:O103) -> 60 | P104: =SUM(P99:P103) -> 4 | Q104: =SUM(Q99:Q103) -> 12.16 | R104: =SUM(R99:R103) -> 0 | S104: =SUM(S99:S103) -> 0 | T104: =SUM(T99:T103) -> 0 | U104: =SUM(U99:U103) -> 0 | V104: =SUM(V99:V103) -> 0 | ... AB104: =SUM(AB99:AB103) -> 186534.4 | AC104: TOT
O105: # of Server | P105: # of Rack Cab | Q105: =ROUNDUP($P104*$D$99,0) -> 11 | W105: =$Q104*$D$101 -> 37306.88
A107: Electricity | O107: # of Servers | P107: kWh / year | R107: 1 | S107: 2 | T107: 3 | U107: 4 | V107: 5 | W107: 1 | X107: 2 | Y107: 3 | Z107: 4 | AA107: 5 | AB107: TOT
A108: Actual Electricity Cost at the sites | C108: €/kWh | D108: =0.1*Data!C1 -> 0.118 | N108: Prod | O108: =$O$19 -> 12 | P108: =$D$111*O108 -> 168192 | W108: =$P108*$D$108 -> 19846.656 | X108: =$P108*$D$108 -> 19846.656 | Y108: =$P108*$D$108 -> 19846.656 | Z108: =$P108*$D$108 -> 19846.656 | AA108: =$P108*$D$108 -> 19846.656 | AB108: =SUM(R108:AA108) -> 99233.28 | AC108: Prod
A109: Electricity Additional Cost for cooling, UPS and other peripherals | C109: % | D109: 0.66 | N109: Dev | O109: =$O$20 -> 6 | P109: =$D$111*O109 -> 84096 | W109: =$P109*$D$108 -> 9923.328 | X109: =$P109*$D$108 -> 9923.328 | Y109: =$P109*$D$108 -> 9923.328 | Z109: =$P109*$D$108 -> 9923.328 | AA109: =$P109*$D$108 -> 9923.328 | AB109: =SUM(R109:AA109) -> 49616.64 | AC109: Dev
A110: Electricity Consumption of Selected Server | C110: kWh | D110: =L5 -> 1.6 | N110: Test | O110: =$O$21 -> 6 | P110: =$D$111*O110 -> 84096 | W110: =$P110*$D$108 -> 9923.328 | X110: =$P110*$D$108 -> 9923.328 | Y110: =$P110*$D$108 -> 9923.328 | Z110: =$P110*$D$108 -> 9923.328 | AA110: =$P110*$D$108 -> 9923.328 | AB110: =SUM(R110:AA110) -> 49616.64 | AC110: Test
...

Sheet LinuxONE TCO
A1: Enterprise Grade Linux Environment | R1: Acquisition/Capital Cost | W1: Maintenance/ Operating Cost | AB1: TOTALS
A2: Typically LinuxONE | R2: 1 | S2: 2 | T2: 3 | U2: 4 | V2: 5 | W2: 1 | X2: 2 | Y2: 3 | Z2: 4 | AA2: 5
A3: Hardware
A4: Linux ONE | C4: Acquisition Cost | D4: Included cores | E4: core cost | F4: CBU Cost | G4: Discount % | H4: # of Cores per Server | I4: Maintenance/ Operating Cost | J4: Starting Year of Maint | K4: kW | O4: SW Incl | P4: SW incl | Q4: SW incl | R4: SW incl
A5: Simplicistic model to build a price example | C5: 600000 | D5: 6 | E5: 50000 | F5: 5000 | G5: 0.3 | H5: 190 | I5: 0.1 | J5: 4 | K5: 15 | O5: OS | P5: VM | Q5: Admin | R5: Management
A6: This is an estimate based on this web page: | C6: https://www.ibm.com/it-infrastructure/resources/tools/linuxone-tco-calculator/
A8: Simplicistic architecture considering always 2 LinuxONE servers, each one in a different site for HA & DR
C9: # of Cores (core) for bare workload | D9: % of Cores vs bare workload | E9: Allocated Cores | F9: Site 1 core | G9: Site 2 core | H9: Site 1 CBU | I9: Site 2 CBU | K9: Allocation % | O9: # of Server | P9: # of Sockets | Q9: # of Cores | R9: 1 | S9: 2 | T9: 3 | U9: 4 | V9: 5 | W9: 1 | X9: 2 | Y9: 3 | Z9: 4 | AA9: 5 | AB9: TOT
A10: Prod | C10: =sizing!D5 -> 40 | D10: see sizing | E10: =sizing!F5 -> 40 | F10: =ROUNDUP(E10,0) -> 40 | I10: =F10 -> 40 | J10: Prod | K10: =$E10/$E$15 -> 0.33333333 | N10: Prod | O10: =K10*2 -> 0.66666667 | P10: =Q10 -> 40 | Q10: =SUM(F10:G10) -> 40 | R10: =$K10*($F$16+$G$16)*(1-$G$5) -> 1540000 | W10: =IF(W$9<$J$5,0,$R10*$I$5) -> 0 | X10: =IF(X$9<$J$5,0,$R10*$I$5) -> 0 | Y10: =IF(Y$9<$J$5,0,$R10*$I$5) -> 0 | Z10: =IF(Z$9<$J$5,0,$R10*$I$5) -> 154000 | AA10: =IF(AA$9<$J$5,0,$R10*$I$5) -> 154000 | AB10: =SUM(R10:AA10) -> 1848000 | AC10: Prod
A11: Dev | D11: =sizing!H5 -> 0.5 | E11: =ROUNDUP($C$10*D11,0) -> 20 | F11: =E11 -> 20 | G11: =E11-F11 -> 0 | J11: Dev | K11: =$E11/$E$15 -> 0.16666667 | N11: Dev | O11: =K11*2 -> 0.33333333 | P11: =Q11 -> 20 | Q11: =SUM(F11:G11) -> 20 | R11: =$K11*($F$16+$G$16)*(1-$G$5) -> 770000 | W11: =IF(W$9<$J$5,0,$R11*$I$5) -> 0 | X11: =IF(X$9<$J$5,0,$R11*$I$5) -> 0 | Y11: =IF(Y$9<$J$5,0,$R11*$I$5) -> 0 | Z11: =IF(Z$9<$J$5,0,$R11*$I$5) -> 77000 | AA11: =IF(AA$9<$J$5,0,$R11*$I$5) -> 77000 | AB11: =SUM(R11:AA11) -> 924000 | AC11: Dev
A12: Test | D12: =sizing!J5 -> 0.5 | E12: =ROUNDUP($C$10*D12,0) -> 20 | F12: =E12-G12 -> 0 | G12: =E12 -> 20 | J12: Test | K12: =$E12/$E$15 -> 0.16666667 | N12: Test | O12: =K12*2 -> 0.33333333 | P12: =Q12 -> 20 | Q12: =SUM(F12:G12) -> 20 | R12: =$K12*($F$16+$G$16)*(1-$G$5) -> 770000 | W12: =IF(W$9<$J$5,0,$R12*$I$5) -> 0 | X12: =IF(X$9<$J$5,0,$R12*$I$5) -> 0 | Y12: =IF(Y$9<$J$5,0,$R12*$I$5) -> 0 | Z12: =IF(Z$9<$J$5,0,$R12*$I$5) -> 77000 | AA12: =IF(AA$9<$J$5,0,$R12*$I$5) -> 77000 | AB12: =SUM(R12:AA12) -> 924000 | AC12: Test
A13: PreProd | D13: =sizing!L5 -> 1 | E13: =ROUNDUP($C$10*D13,0) -> 40 | G13: =C10 -> 40 | H13: =G13 -> 40 | J13: QA | K13: =$E13/$E$15 -> 0.33333333 | N13: QA | O13: =K13*2 -> 0.66666667 | P13: =Q13 -> 40 | Q13: =SUM(F13:G13) -> 40 | R13: =$K13*($F$16+$G$16)*(1-$G$5) -> 1540000 | W13: =IF(W$9<$J$5,0,$R13*$I$5) -> 0 | X13: =IF(X$9<$J$5,0,$R13*$I$5) -> 0 | Y13: =IF(Y$9<$J$5,0,$R13*$I$5) -> 0 | Z13: =IF(Z$9<$J$5,0,$R13*$I$5) -> 154000 | AA13: =IF(AA$9<$J$5,0,$R13*$I$5) -> 154000 | AB13: =SUM(R13:AA13) -> 1848000 | AC13: QA
A14: DR | H14: =SUM(H10:H13) -> 40 | I14: =SUM(I10:I13) -> 40 | J14: DR | N14: DR | R14: =($H$16+$I$16)*(1-$G$5) -> 280000 | W14: =IF(W$9<$J$5,0,$R14*$I$5) -> 0 | X14: =IF(X$9<$J$5,0,$R14*$I$5) -> 0 | Y14: =IF(Y$9<$J$5,0,$R14*$I$5) -> 0 | Z14: =IF(Z$9<$J$5,0,$R14*$I$5) -> 28000 | AA14: =IF(AA$9<$J$5,0,$R14*$I$5) -> 28000 | AB14: =SUM(R14:AA14) -> 336000 | AC14: DR
A15: TOT | E15: =SUM(E10:E14) -> 120 | F15: =SUM(F10:F14) -> 60 | G15: =SUM(G10:G14) -> 60 | H15: =H14 -> 40 | I15: =I14 -> 40 | K15: =SUM(K10:K14) -> 1 | O15: =SUM(O10:O14) -> 2 | P15: =SUM(P10:P14) -> 120 | Q15: =SUM(Q10:Q14) -> 120 | R15: =SUM(R10:R14) -> 4900000 | S15: =SUM(S10:S14) -> 0 | T15: =SUM(T10:T14) -> 0 | U15: =SUM(U10:U14) -> 0 | V15: =SUM(V10:V14) -> 0 | ... AB15: =SUM(AB10:AB14) -> 5880000 | AC15: TOT
E16: Price per Site | F16: =IF($D$5<F15,((F15-$D$5)*$E$5+$C$5),$C$5) -> 3300000 | G16: =IF($D$5<G15,((G15-$D$5)*$E$5+$C$5),$C$5) -> 3300000 | H16: =($H$15*$F$5) -> 200000 | I16: =($I$15*$F$5) -> 200000 | O16: # of Server | P16: # of Sockets | Q16: # of Cores
A22: Software Stack
A23: Production | C23: Acquisition/ Capital Cost | D23: Maintenance/ Subscription | E23: Starting Year of Maint charges | F23: Discount % | G23: Unit of Measure | H23: Measured by | I23: conversion factor | J23: server | K23: socket | L23: core | O23: count | P23: Unit of Measure | Q23: Units | R23: 1 | S23: 2 | T23: 3 | U23: 4 | V23: 5 | W23: 1 | X23: 2 | Y23: 3 | Z23: 4 | AA23: 5 | AB23: TOT
A24: OS | D24: 6000 | E24: 1 | F24: 0.2 | G24: core | H24: core | I24: 1 | J24: =$O$10 -> 0.66666667 | K24: =$P$10 -> 40 | L24: =$Q$10 -> 40 | O24: =_xlfn.XLOOKUP($H24,$J$23:$L$23,$J24:$L24) -> 40 | P24: socket | Q24: =I24*O24 -> 40 | R24: =$Q24*$C24*(1-$F24) -> 0 | W24: =IF(W$9<$E24,0,$Q24*$D24)*(1-$F24) -> 192000 | X24: =IF(X$9<$E24,0,$Q24*$D24)*(1-$F24) -> 192000 | Y24: =IF(Y$9<$E24,0,$Q24*$D24)*(1-$F24) -> 192000 | Z24: =IF(Z$9<$E24,0,$Q24*$D24)*(1-$F24) -> 192000 | AA24: =IF(AA$9<$E24,0,$Q24*$D24)*(1-$F24) -> 192000 | AB24: =SUM(R24:AA24) -> 960000
A25: VM | E25: 2 | F25: 0.2 | G25: core | H25: core | I25: 1 | J25: =J24 -> 0.66666667 | K25: =K24 -> 40 | L25: =L24 -> 40 | O25: =_xlfn.XLOOKUP($H25,$J$23:$L$23,$J25:$L25) -> 40 | P25: socket | Q25: =I25*O25 -> 40 | R25: =$Q25*$C25*(1-$F25) -> 0 | W25: =IF(W$9<$E25,0,$Q25*$D25)*(1-$F25) -> 0 | X25: =IF(X$9<$E25,0,$Q25*$D25)*(1-$F25) -> 0 | Y25: =IF(Y$9<$E25,0,$Q25*$D25)*(1-$F25) -> 0 | Z25: =IF(Z$9<$E25,0,$Q25*$D25)*(1-$F25) -> 0 | AA25: =IF(AA$9<$E25,0,$Q25*$D25)*(1-$F25) -> 0 | AB25: =SUM(R25:AA25) -> 0
A26: Application Server | C26: =Data!B12 -> 46.82 | D26: =Data!C12 -> 9.36 | E26: =Data!D12 -> 2 | F26: 0.5 | G26: =Data!E12 -> PVU | H26: =Data!F12 -> core | I26: 120 | J26: =J25 -> 0.66666667 | K26: =K25 -> 40 | L26: =L25 -> 40 | O26: =_xlfn.XLOOKUP($H26,$J$23:$L$23,$J26:$L26) -> 40 | P26: PVU | Q26: =I26*O26 -> 4800 | R26: =$Q26*$C26*(1-$F26) -> 112368 | W26: =IF(W$9<$E26,0,$Q26*$D26)*(1-$F26) -> 0 | X26: =IF(X$9<$E26,0,$Q26*$D26)*(1-$F26) -> 22464 | Y26: =IF(Y$9<$E26,0,$Q26*$D26)*(1-$F26) -> 22464 | Z26: =IF(Z$9<$E26,0,$Q26*$D26)*(1-$F26) -> 22464 | AA26: =IF(AA$9<$E26,0,$Q26*$D26)*(1-$F26) -> 22464 | AB26: =SUM(R26:AA26) -> 202224
A27: DB | C27: =Data!B25 -> 0 | D27: =Data!C25 -> 8500 | E27: =Data!D25 -> 1 | F27: 0 | G27: =Data!E25 -> server | H27: =Data!F25 -> server | I27: 1 | J27: =J26 -> 0.66666667 | K27: =K26 -> 40 | L27: =L26 -> 40 | O27: =_xlfn.XLOOKUP($H27,$J$23:$L$23,$J27:$L27) -> 0.66666667 | P27: core | Q27: =I27*O27 -> 0.66666667 | R27: =$Q27*$C27*(1-$F27) -> 0 | W27: =IF(W$9<$E27,0,$Q27*$D27)*(1-$F27) -> 5666.6667 | X27: =IF(X$9<$E27,0,$Q27*$D27)*(1-$F27) -> 5666.6667 | Y27: =IF(Y$9<$E27,0,$Q27*$D27)*(1-$F27) -> 5666.6667 | Z27: =IF(Z$9<$E27,0,$Q27*$D27)*(1-$F27) -> 5666.6667 | AA27: =IF(AA$9<$E27,0,$Q27*$D27)*(1-$F27) -> 5666.6667 | AB27: =SUM(R27:AA27) -> 28333.333
A28: Data Replication Tools | D28: 3000 | E28: 1 | F28: 0.5 | G28: core | H28: core | I28: 1 | J28: =J27 -> 0.66666667 | K28: =K27 -> 40 | L28: =L27 -> 40 | O28: =_xlfn.XLOOKUP($H28,$J$23:$L$23,$J28:$L28) -> 40 | P28: core | Q28: =I28*O28 -> 40 | R28: =$Q28*$C28*(1-$F28) -> 0 | W28: =IF(W$9<$E28,0,$Q28*$D28)*(1-$F28) -> 60000 | X28: =IF(X$9<$E28,0,$Q28*$D28)*(1-$F28) -> 60000 | Y28: =IF(Y$9<$E28,0,$Q28*$D28)*(1-$F28) -> 60000 | Z28: =IF(Z$9<$E28,0,$Q28*$D28)*(1-$F28) -> 60000 | AA28: =IF(AA$9<$E28,0,$Q28*$D28)*(1-$F28) -> 60000 | AB28: =SUM(R28:AA28) -> 300000
A29: Monitoring Tools | C29: 5000 | D29: =C29*0.2 -> 1000 | E29: 2 | F29: 0.4 | G29: server | H29: server | I29: 1 | J29: =J28 -> 0.66666667 | K29: =K28 -> 40 | L29: =L28 -> 40 | O29: =_xlfn.XLOOKUP($H29,$J$23:$L$23,$J29:$L29) -> 0.66666667 | P29: server | Q29: =I29*O29 -> 0.66666667 | R29: =$Q29*$C29*(1-$F29) -> 2000 | W29: =IF(W$9<$E29,0,$Q29*$D29)*(1-$F29) -> 0 | X29: =IF(X$9<$E29,0,$Q29*$D29)*(1-$F29) -> 400 | Y29: =IF(Y$9<$E29,0,$Q29*$D29)*(1-$F29) -> 400 | Z29: =IF(Z$9<$E29,0,$Q29*$D29)*(1-$F29) -> 400 | AA29: =IF(AA$9<$E29,0,$Q29*$D29)*(1-$F29) -> 400 | AB29: =SUM(R29:AA29) -> 3600
A30: Security Tools | C30: 5000 | D30: =C30*0.2 -> 1000 | E30: 2 | F30: 0.4 | G30: server | H30: server | I30: 1 | J30: =J29 -> 0.66666667 | K30: =K29 -> 40 | L30: =L29 -> 40 | O30: =_xlfn.XLOOKUP($H30,$J$23:$L$23,$J30:$L30) -> 0.66666667 | P30: server | Q30: =I30*O30 -> 0.66666667 | R30: =$Q30*$C30*(1-$F30) -> 2000 | W30: =IF(W$9<$E30,0,$Q30*$D30)*(1-$F30) -> 0 | X30: =IF(X$9<$E30,0,$Q30*$D30)*(1-$F30) -> 400 | Y30: =IF(Y$9<$E30,0,$Q30*$D30)*(1-$F30) -> 400 | Z30: =IF(Z$9<$E30,0,$Q30*$D30)*(1-$F30) -> 400 | AA30: =IF(AA$9<$E30,0,$Q30*$D30)*(1-$F30) -> 400 | AB30: =SUM(R30:AA30) -> 3600
Q31: PROD | R31: =SUM(R24:R30) -> 116368 | S31: =SUM(S24:S30) -> 0 | T31: =SUM(T24:T30) -> 0 | U31: =SUM(U24:U30) -> 0 | V31: =SUM(V24:V30) -> 0 | W31: =SUM(W24:W30) -> 257666.67 | X31: =SUM(X24:X30) -> 280930.67 | Y31: =SUM(Y24:Y30) -> 280930.67 | ... AB31: =SUM(AB24:AB30) -> 1497757.3
A33: Dev | C33: =C23 -> Acquisition/ Capital Cost | D33: =D23 -> Maintenance/ Subscription | E33: Starting Year of Maint charges | F33: Discount % | G33: Unit of Measure | H33: Measured by | I33: conversion factor | J33: server | K33: socket | L33: core | O33: count | P33: Unit of Measure | Q33: Units | R33: 1 | S33: 2 | T33: 3 | U33: 4 | V33: 5 | W33: 1 | X33: 2 | Y33: 3 | Z33: 4 | AA33: 5 | AB33: TOT
A34: =A24 -> OS | C34: =C24 -> 0 | D34: =D24 -> 6000 | E34: =E24 -> 1 | F34: =F24 -> 0.2 | G34: =G24 -> core | H34: =H24 -> core | I34: =I24 -> 1 | J34: =$O$11 -> 0.33333333 | K34: =$P$11 -> 20 | L34: =$Q$11 -> 20 | O34: =_xlfn.XLOOKUP($H34,$J$23:$L$23,$J34:$L34) -> 20 | P34: socket | Q34: =I34*O34 -> 20 | R34: =$Q34*$C34*(1-$F34) -> 0 | W34: =IF(W$9<$E34,0,$Q34*$D34)*(1-$F34) -> 96000 | X34: =IF(X$9<$E34,0,$Q34*$D34)*(1-$F34) -> 96000 | Y34: =IF(Y$9<$E34,0,$Q34*$D34)*(1-$F34) -> 96000 | Z34: =IF(Z$9<$E34,0,$Q34*$D34)*(1-$F34) -> 96000 | AA34: =IF(AA$9<$E34,0,$Q34*$D34)*(1-$F34) -> 96000 | AB34: =SUM(R34:AA34) -> 480000
A35: =A25 -> VM | C35: =C25 -> 0 | D35: =D25 -> 0 | E35: =E25 -> 2 | F35: =F25 -> 0.2 | G35: =G25 -> core | H35: =H25 -> core | I35: =I25 -> 1 | J35: =J34 -> 0.33333333 | K35: =K34 -> 20 | L35: =L34 -> 20 | O35: =_xlfn.XLOOKUP($H35,$J$23:$L$23,$J35:$L35) -> 20 | P35: socket | Q35: =I35*O35 -> 20 | R35: =$Q35*$C35*(1-$F35) -> 0 | W35: =IF(W$9<$E35,0,$Q35*$D35)*(1-$F35) -> 0 | X35: =IF(X$9<$E35,0,$Q35*$D35)*(1-$F35) -> 0 | Y35: =IF(Y$9<$E35,0,$Q35*$D35)*(1-$F35) -> 0 | Z35: =IF(Z$9<$E35,0,$Q35*$D35)*(1-$F35) -> 0 | AA35: =IF(AA$9<$E35,0,$Q35*$D35)*(1-$F35) -> 0 | AB35: =SUM(R35:AA35) -> 0
A36: =A26 -> Application Server | C36: =C26 -> 46.82 | D36: =D26 -> 9.36 | E36: =E26 -> 2 | F36: =F26 -> 0.5 | G36: =G26 -> PVU | H36: =H26 -> core | I36: =I26 -> 120 | J36: =J35 -> 0.33333333 | K36: =K35 -> 20 | L36: =L35 -> 20 | O36: =_xlfn.XLOOKUP($H36,$J$23:$L$23,$J36:$L36) -> 20 | P36: PVU | Q36: =I36*O36 -> 2400 | R36: =$Q36*$C36*(1-$F36) -> 56184 | W36: =IF(W$9<$E36,0,$Q36*$D36)*(1-$F36) -> 0 | X36: =IF(X$9<$E36,0,$Q36*$D36)*(1-$F36) -> 11232 | Y36: =IF(Y$9<$E36,0,$Q36*$D36)*(1-$F36) -> 11232 | Z36: =IF(Z$9<$E36,0,$Q36*$D36)*(1-$F36) -> 11232 | AA36: =IF(AA$9<$E36,0,$Q36*$D36)*(1-$F36) -> 11232 | AB36: =SUM(R36:AA36) -> 101112
A37: =A27 -> DB | C37: =C27 -> 0 | D37: =D27 -> 8500 | E37: =E27 -> 1 | F37: =F27 -> 0 | G37: =G27 -> server | H37: =H27 -> server | I37: =I27 -> 1 | J37: =J36 -> 0.33333333 | K37: =K36 -> 20 | L37: =L36 -> 20 | O37: =_xlfn.XLOOKUP($H37,$J$23:$L$23,$J37:$L37) -> 0.33333333 | P37: core | Q37: =I37*O37 -> 0.33333333 | R37: =$Q37*$C37*(1-$F37) -> 0 | W37: =IF(W$9<$E37,0,$Q37*$D37)*(1-$F37) -> 2833.3333 | X37: =IF(X$9<$E37,0,$Q37*$D37)*(1-$F37) -> 2833.3333 | Y37: =IF(Y$9<$E37,0,$Q37*$D37)*(1-$F37) -> 2833.3333 | Z37: =IF(Z$9<$E37,0,$Q37*$D37)*(1-$F37) -> 2833.3333 | AA37: =IF(AA$9<$E37,0,$Q37*$D37)*(1-$F37) -> 2833.3333 | AB37: =SUM(R37:AA37) -> 14166.667
A38: =A28 -> Data Replication Tools | C38: =C28 -> 0 | D38: =D28 -> 3000 | E38: =E28 -> 1 | F38: =F28 -> 0.5 | G38: =G28 -> core | H38: =H28 -> core | I38: =I28 -> 1 | J38: =J37 -> 0.33333333 | K38: =K37 -> 20 | L38: =L37 -> 20 | O38: =_xlfn.XLOOKUP($H38,$J$23:$L$23,$J38:$L38) -> 20 | P38: core | Q38: =I38*O38 -> 20 | R38: =$Q38*$C38*(1-$F38) -> 0 | W38: =IF(W$9<$E38,0,$Q38*$D38)*(1-$F38) -> 30000 | X38: =IF(X$9<$E38,0,$Q38*$D38)*(1-$F38) -> 30000 | Y38: =IF(Y$9<$E38,0,$Q38*$D38)*(1-$F38) -> 30000 | Z38: =IF(Z$9<$E38,0,$Q38*$D38)*(1-$F38) -> 30000 | AA38: =IF(AA$9<$E38,0,$Q38*$D38)*(1-$F38) -> 30000 | AB38: =SUM(R38:AA38) -> 150000
A39: =A29 -> Monitoring Tools | C39: =C29 -> 5000 | D39: =D29 -> 1000 | E39: =E29 -> 2 | F39: =F29 -> 0.4 | G39: =G29 -> server | H39: =H29 -> server | I39: =I29 -> 1 | J39: =J38 -> 0.33333333 | K39: =K38 -> 20 | L39: =L38 -> 20 | O39: =_xlfn.XLOOKUP($H39,$J$23:$L$23,$J39:$L39) -> 0.33333333 | P39: server | Q39: =I39*O39 -> 0.33333333 | R39: =$Q39*$C39*(1-$F39) -> 1000 | W39: =IF(W$9<$E39,0,$Q39*$D39)*(1-$F39) -> 0 | X39: =IF(X$9<$E39,0,$Q39*$D39)*(1-$F39) -> 200 | Y39: =IF(Y$9<$E39,0,$Q39*$D39)*(1-$F39) -> 200 | Z39: =IF(Z$9<$E39,0,$Q39*$D39)*(1-$F39) -> 200 | AA39: =IF(AA$9<$E39,0,$Q39*$D39)*(1-$F39) -> 200 | AB39: =SUM(R39:AA39) -> 1800
A40: =A30 -> Security Tools | C40: =C30 -> 5000 | D40: =D30 -> 1000 | E40: =E30 -> 2 | F40: =F30 -> 0.4 | G40: =G30 -> server | H40: =H30 -> server | I40: =I30 -> 1 | J40: =J39 -> 0.33333333 | K40: =K39 -> 20 | L40: =L39 -> 20 | O40: =_xlfn.XLOOKUP($H40,$J$23:$L$23,$J40:$L40) -> 0.33333333 | P40: server | Q40: =I40*O40 -> 0.33333333 | R40: =$Q40*$C40*(1-$F40) -> 1000 | W40: =IF(W$9<$E40,0,$Q40*$D40)*(1-$F40) -> 0 | X40: =IF(X$9<$E40,0,$Q40*$D40)*(1-$F40) -> 200 | Y40: =IF(Y$9<$E40,0,$Q40*$D40)*(1-$F40) -> 200 | Z40: =IF(Z$9<$E40,0,$Q40*$D40)*(1-$F40) -> 200 | AA40: =IF(AA$9<$E40,0,$Q40*$D40)*(1-$F40) -> 200 | AB40: =SUM(R40:AA40) -> 1800
Q41: DEV | R41: =SUM(R34:R40) -> 58184 | S41: =SUM(S34:S40) -> 0 | T41: =SUM(T34:T40) -> 0 | U41: =SUM(U34:U40) -> 0 | V41: =SUM(V34:V40) -> 0 | W41: =SUM(W34:W40) -> 128833.33 | X41: =SUM(X34:X40) -> 140465.33 | Y41: =SUM(Y34:Y40) -> 140465.33 | ... AB41: =SUM(AB34:AB40) -> 748878.67
A43: Test | C43: Acquisition/ Capital Cost | D43: Maintenance/ Operating Cost | E43: Starting Year of Maint charges | F43: Discount % | G43: Unit of Measure | H43: Measured by | I43: conversion factor | J43: server | K43: socket | L43: core | O43: count | P43: Unit of Measure | Q43: Units | R43: 1 | S43: 2 | T43: 3 | U43: 4 | V43: 5 | W43: 1 | X43: 2 | Y43: 3 | Z43: 4 | AA43: 5 | AB43: TOT
A44: =A24 -> OS | C44: =C24 -> 0 | D44: =D24 -> 6000 | E44: =E24 -> 1 | F44: =F24 -> 0.2 | G44: =G34 -> core | H44: =H34 -> core | I44: =I34 -> 1 | J44: =$O$12 -> 0.33333333 | K44: =$P$12 -> 20 | L44: =$Q$12 -> 20 | O44: =_xlfn.XLOOKUP($H44,$J$23:$L$23,$J44:$L44) -> 20 | P44: socket | Q44: =I44*O44 -> 20 | R44: =$Q44*$C44*(1-$F44) -> 0 | W44: =IF(W$9<$E44,0,$Q44*$D44)*(1-$F44) -> 96000 | X44: =IF(X$9<$E44,0,$Q44*$D44)*(1-$F44) -> 96000 | Y44: =IF(Y$9<$E44,0,$Q44*$D44)*(1-$F44) -> 96000 | Z44: =IF(Z$9<$E44,0,$Q44*$D44)*(1-$F44) -> 96000 | AA44: =IF(AA$9<$E44,0,$Q44*$D44)*(1-$F44) -> 96000 | AB44: =SUM(R44:AA44) -> 480000
A45: =A25 -> VM | C45: =C25 -> 0 | D45: =D25 -> 0 | E45: =E25 -> 2 | F45: =F25 -> 0.2 | G45: =G35 -> core | H45: =H35 -> core | I45: =I35 -> 1 | J45: =J44 -> 0.33333333 | K45: =K44 -> 20 | L45: =L44 -> 20 | O45: =_xlfn.XLOOKUP($H45,$J$23:$L$23,$J45:$L45) -> 20 | P45: socket | Q45: =I45*O45 -> 20 | R45: =$Q45*$C45*(1-$F45) -> 0 | W45: =IF(W$9<$E45,0,$Q45*$D45)*(1-$F45) -> 0 | X45: =IF(X$9<$E45,0,$Q45*$D45)*(1-$F45) -> 0 | Y45: =IF(Y$9<$E45,0,$Q45*$D45)*(1-$F45) -> 0 | Z45: =IF(Z$9<$E45,0,$Q45*$D45)*(1-$F45) -> 0 | AA45: =IF(AA$9<$E45,0,$Q45*$D45)*(1-$F45) -> 0 | AB45: =SUM(R45:AA45) -> 0
A46: =A26 -> Application Server | C46: =C26 -> 46.82 | D46: =D26 -> 9.36 | E46: =E26 -> 2 | F46: =F26 -> 0.5 | G46: =G36 -> PVU | H46: =H36 -> core | I46: =I36 -> 120 | J46: =J45 -> 0.33333333 | K46: =K45 -> 20 | L46: =L45 -> 20 | O46: =_xlfn.XLOOKUP($H46,$J$23:$L$23,$J46:$L46) -> 20 | P46: PVU | Q46: =I46*O46 -> 2400 | R46: =$Q46*$C46*(1-$F46) -> 56184 | W46: =IF(W$9<$E46,0,$Q46*$D46)*(1-$F46) -> 0 | X46: =IF(X$9<$E46,0,$Q46*$D46)*(1-$F46) -> 11232 | Y46: =IF(Y$9<$E46,0,$Q46*$D46)*(1-$F46) -> 11232 | Z46: =IF(Z$9<$E46,0,$Q46*$D46)*(1-$F46) -> 11232 | AA46: =IF(AA$9<$E46,0,$Q46*$D46)*(1-$F46) -> 11232 | AB46: =SUM(R46:AA46) -> 101112
A47: =A27 -> DB | C47: =C27 -> 0 | D47: =D27 -> 8500 | E47: =E27 -> 1 | F47: =F27 -> 0 | G47: =G37 -> server | H47: =H37 -> server | I47: =I37 -> 1 | J47: =J46 -> 0.33333333 | K47: =K46 -> 20 | L47: =L46 -> 20 | O47: =_xlfn.XLOOKUP($H47,$J$23:$L$23,$J47:$L47) -> 0.33333333 | P47: core | Q47: =I47*O47 -> 0.33333333 | R47: =$Q47*$C47*(1-$F47) -> 0 | W47: =IF(W$9<$E47,0,$Q47*$D47)*(1-$F47) -> 2833.3333 | X47: =IF(X$9<$E47,0,$Q47*$D47)*(1-$F47) -> 2833.3333 | Y47: =IF(Y$9<$E47,0,$Q47*$D47)*(1-$F47) -> 2833.3333 | Z47: =IF(Z$9<$E47,0,$Q47*$D47)*(1-$F47) -> 2833.3333 | AA47: =IF(AA$9<$E47,0,$Q47*$D47)*(1-$F47) -> 2833.3333 | AB47: =SUM(R47:AA47) -> 14166.667
A48: =A28 -> Data Replication Tools | C48: =C28 -> 0 | D48: =D28 -> 3000 | E48: =E28 -> 1 | F48: =F28 -> 0.5 | G48: =G38 -> core | H48: =H38 -> core | I48: =I38 -> 1 | J48: =J47 -> 0.33333333 | K48: =K47 -> 20 | L48: =L47 -> 20 | O48: =_xlfn.XLOOKUP($H48,$J$23:$L$23,$J48:$L48) -> 20 | P48: core | Q48: =I48*O48 -> 20 | R48: =$Q48*$C48*(1-$F48) -> 0 | W48: =IF(W$9<$E48,0,$Q48*$D48)*(1-$F48) -> 30000 | X48: =IF(X$9<$E48,0,$Q48*$D48)*(1-$F48) -> 30000 | Y48: =IF(Y$9<$E48,0,$Q48*$D48)*(1-$F48) -> 30000 | Z48: =IF(Z$9<$E48,0,$Q48*$D48)*(1-$F48) -> 30000 | AA48: =IF(AA$9<$E48,0,$Q48*$D48)*(1-$F48) -> 30000 | AB48: =SUM(R48:AA48) -> 150000
A49: =A29 -> Monitoring Tools | C49: =C29 -> 5000 | D49: =D29 -> 1000 | E49: =E29 -> 2 | F49: =F29 -> 0.4 | G49: =G39 -> server | H49: =H39 -> server | I49: =I39 -> 1 | J49: =J48 -> 0.33333333 | K49: =K48 -> 20 | L49: =L48 -> 20 | O49: =_xlfn.XLOOKUP($H49,$J$23:$L$23,$J49:$L49) -> 0.33333333 | P49: server | Q49: =I49*O49 -> 0.33333333 | R49: =$Q49*$C49*(1-$F49) -> 1000 | W49: =IF(W$9<$E49,0,$Q49*$D49)*(1-$F49) -> 0 | X49: =IF(X$9<$E49,0,$Q49*$D49)*(1-$F49) -> 200 | Y49: =IF(Y$9<$E49,0,$Q49*$D49)*(1-$F49) -> 200 | Z49: =IF(Z$9<$E49,0,$Q49*$D49)*(1-$F49) -> 200 | AA49: =IF(AA$9<$E49,0,$Q49*$D49)*(1-$F49) -> 200 | AB49: =SUM(R49:AA49) -> 1800
A50: =A30 -> Security Tools | C50: =C30 -> 5000 | D50: =D30 -> 1000 | E50: =E30 -> 2 | F50: =F30 -> 0.4 | G50: =G40 -> server | H50: =H40 -> server | I50: =I40 -> 1 | J50: =J49 -> 0.33333333 | K50: =K49 -> 20 | L50: =L49 -> 20 | O50: =_xlfn.XLOOKUP($H50,$J$23:$L$23,$J50:$L50) -> 0.33333333 | P50: server | Q50: =I50*O50 -> 0.33333333 | R50: =$Q50*$C50*(1-$F50) -> 1000 | W50: =IF(W$9<$E50,0,$Q50*$D50)*(1-$F50) -> 0 | X50: =IF(X$9<$E50,0,$Q50*$D50)*(1-$F50) -> 200 | Y50: =IF(Y$9<$E50,0,$Q50*$D50)*(1-$F50) -> 200 | Z50: =IF(Z$9<$E50,0,$Q50*$D50)*(1-$F50) -> 200 | AA50: =IF(AA$9<$E50,0,$Q50*$D50)*(1-$F50) -> 200 | AB50: =SUM(R50:AA50) -> 1800
Q51: Test | R51: =SUM(R44:R50) -> 58184 | S51: =SUM(S44:S50) -> 0 | T51: =SUM(T44:T50) -> 0 | U51: =SUM(U44:U50) -> 0 | V51: =SUM(V44:V50) -> 0 | W51: =SUM(W44:W50) -> 128833.33 | X51: =SUM(X44:X50) -> 140465.33 | Y51: =SUM(Y44:Y50) -> 140465.33 | ... AB51: =SUM(AB44:AB50) -> 748878.67
A53: Pre Prod / QA | C53: Acquisition/ Capital Cost | D53: Maintenance/ Operating Cost | E53: Starting Year of Maint charges | F53: Discount % | G53: Unit of Measure | H53: Measured by | I53: conversion factor | J53: server | K53: socket | L53: core | O53: count | P53: Unit of Measure | Q53: Units | R53: 1 | S53: 2 | T53: 3 | U53: 4 | V53: 5 | W53: 1 | X53: 2 | Y53: 3 | Z53: 4 | AA53: 5 | AB53: TOT
A54: =A24 -> OS | C54: =C24 -> 0 | D54: =D24 -> 6000 | E54: =E24 -> 1 | F54: =F24 -> 0.2 | G54: =G44 -> core | H54: =H44 -> core | I54: =I44 -> 1 | J54: =$O$13 -> 0.66666667 | K54: =$P$13 -> 40 | L54: =$Q$13 -> 40 | O54: =_xlfn.XLOOKUP($H54,$J$23:$L$23,$J54:$L54) -> 40 | P54: socket | Q54: =I54*O54 -> 40 | R54: =$Q54*$C54*(1-$F54) -> 0 | W54: =IF(W$9<$E54,0,$Q54*$D54)*(1-$F54) -> 192000 | X54: =IF(X$9<$E54,0,$Q54*$D54)*(1-$F54) -> 192000 | Y54: =IF(Y$9<$E54,0,$Q54*$D54)*(1-$F54) -> 192000 | Z54: =IF(Z$9<$E54,0,$Q54*$D54)*(1-$F54) -> 192000 | AA54: =IF(AA$9<$E54,0,$Q54*$D54)*(1-$F54) -> 192000 | AB54: =SUM(R54:AA54) -> 960000
A55: =A25 -> VM | C55: =C25 -> 0 | D55: =D25 -> 0 | E55: =E25 -> 2 | F55: =F25 -> 0.2 | G55: =G45 -> core | H55: =H45 -> core | I55: =I45 -> 1 | J55: =J54 -> 0.66666667 | K55: =K54 -> 40 | L55: =L54 -> 40 | O55: =_xlfn.XLOOKUP($H55,$J$23:$L$23,$J55:$L55) -> 40 | P55: socket | Q55: =I55*O55 -> 40 | R55: =$Q55*$C55*(1-$F55) -> 0 | W55: =IF(W$9<$E55,0,$Q55*$D55)*(1-$F55) -> 0 | X55: =IF(X$9<$E55,0,$Q55*$D55)*(1-$F55) -> 0 | Y55: =IF(Y$9<$E55,0,$Q55*$D55)*(1-$F55) -> 0 | Z55: =IF(Z$9<$E55,0,$Q55*$D55)*(1-$F55) -> 0 | AA55: =IF(AA$9<$E55,0,$Q55*$D55)*(1-$F55) -> 0 | AB55: =SUM(R55:AA55) -> 0
A56: =A26 -> Application Server | C56: =C26 -> 46.82 | D56: =D26 -> 9.36 | E56: =E26 -> 2 | F56: =F26 -> 0.5 | G56: =G46 -> PVU | H56: =H46 -> core | I56: =I46 -> 120 | J56: =J55 -> 0.66666667 | K56: =K55 -> 40 | L56: =L55 -> 40 | O56: =_xlfn.XLOOKUP($H56,$J$23:$L$23,$J56:$L56) -> 40 | P56: PVU | Q56: =I56*O56 -> 4800 | R56: =$Q56*$C56*(1-$F56) -> 112368 | W56: =IF(W$9<$E56,0,$Q56*$D56)*(1-$F56) -> 0 | X56: =IF(X$9<$E56,0,$Q56*$D56)*(1-$F56) -> 22464 | Y56: =IF(Y$9<$E56,0,$Q56*$D56)*(1-$F56) -> 22464 | Z56: =IF(Z$9<$E56,0,$Q56*$D56)*(1-$F56) -> 22464 | AA56: =IF(AA$9<$E56,0,$Q56*$D56)*(1-$F56) -> 22464 | AB56: =SUM(R56:AA56) -> 202224
A57: =A27 -> DB | C57: =C27 -> 0 | D57: =D27 -> 8500 | E57: =E27 -> 1 | F57: =F27 -> 0 | G57: =G47 -> server | H57: =H47 -> server | I57: =I47 -> 1 | J57: =J56 -> 0.66666667 | K57: =K56 -> 40 | L57: =L56 -> 40 | O57: =_xlfn.XLOOKUP($H57,$J$23:$L$23,$J57:$L57) -> 0.66666667 | P57: core | Q57: =I57*O57 -> 0.66666667 | R57: =$Q57*$C57*(1-$F57) -> 0 | W57: =IF(W$9<$E57,0,$Q57*$D57)*(1-$F57) -> 5666.6667 | X57: =IF(X$9<$E57,0,$Q57*$D57)*(1-$F57) -> 5666.6667 | Y57: =IF(Y$9<$E57,0,$Q57*$D57)*(1-$F57) -> 5666.6667 | Z57: =IF(Z$9<$E57,0,$Q57*$D57)*(1-$F57) -> 5666.6667 | AA57: =IF(AA$9<$E57,0,$Q57*$D57)*(1-$F57) -> 5666.6667 | AB57: =SUM(R57:AA57) -> 28333.333
A58: =A28 -> Data Replication Tools | C58: =C28 -> 0 | D58: =D28 -> 3000 | E58: =E28 -> 1 | F58: =F28 -> 0.5 | G58: =G48 -> core | H58: =H48 -> core | I58: =I48 -> 1 | J58: =J57 -> 0.66666667 | K58: =K57 -> 40 | L58: =L57 -> 40 | O58: =_xlfn.XLOOKUP($H58,$J$23:$L$23,$J58:$L58) -> 40 | P58: core | Q58: =I58*O58 -> 40 | R58: =$Q58*$C58*(1-$F58) -> 0 | W58: =IF(W$9<$E58,0,$Q58*$D58)*(1-$F58) -> 60000 | X58: =IF(X$9<$E58,0,$Q58*$D58)*(1-$F58) -> 60000 | Y58: =IF(Y$9<$E58,0,$Q58*$D58)*(1-$F58) -> 60000 | Z58: =IF(Z$9<$E58,0,$Q58*$D58)*(1-$F58) -> 60000 | AA58: =IF(AA$9<$E58,0,$Q58*$D58)*(1-$F58) -> 60000 | AB58: =SUM(R58:AA58) -> 300000
A59: =A29 -> Monitoring Tools | C59: =C29 -> 5000 | D59: =D29 -> 1000 | E59: =E29 -> 2 | F59: =F29 -> 0.4 | G59: =G49 -> server | H59: =H49 -> server | I59: =I49 -> 1 | J59: =J58 -> 0.66666667 | K59: =K58 -> 40 | L59: =L58 -> 40 | O59: =_xlfn.XLOOKUP($H59,$J$23:$L$23,$J59:$L59) -> 0.66666667 | P59: server | Q59: =I59*O59 -> 0.66666667 | R59: =$Q59*$C59*(1-$F59) -> 2000 | W59: =IF(W$9<$E59,0,$Q59*$D59)*(1-$F59) -> 0 | X59: =IF(X$9<$E59,0,$Q59*$D59)*(1-$F59) -> 400 | Y59: =IF(Y$9<$E59,0,$Q59*$D59)*(1-$F59) -> 400 | Z59: =IF(Z$9<$E59,0,$Q59*$D59)*(1-$F59) -> 400 | AA59: =IF(AA$9<$E59,0,$Q59*$D59)*(1-$F59) -> 400 | AB59: =SUM(R59:AA59) -> 3600
A60: =A30 -> Security Tools | C60: =C30 -> 5000 | D60: =D30 -> 1000 | E60: =E30 -> 2 | F60: =F30 -> 0.4 | G60: =G50 -> server | H60: =H50 -> server | I60: =I50 -> 1 | J60: =J59 -> 0.66666667 | K60: =K59 -> 40 | L60: =L59 -> 40 | O60: =_xlfn.XLOOKUP($H60,$J$23:$L$23,$J60:$L60) -> 0.66666667 | P60: server | Q60: =I60*O60 -> 0.66666667 | R60: =$Q60*$C60*(1-$F60) -> 2000 | W60: =IF(W$9<$E60,0,$Q60*$D60)*(1-$F60) -> 0 | X60: =IF(X$9<$E60,0,$Q60*$D60)*(1-$F60) -> 400 | Y60: =IF(Y$9<$E60,0,$Q60*$D60)*(1-$F60) -> 400 | Z60: =IF(Z$9<$E60,0,$Q60*$D60)*(1-$F60) -> 400 | AA60: =IF(AA$9<$E60,0,$Q60*$D60)*(1-$F60) -> 400 | AB60: =SUM(R60:AA60) -> 3600
Q61: Pre Prod /QA | R61: =SUM(R54:R60) -> 116368 | S61: =SUM(S54:S60) -> 0 | T61: =SUM(T54:T60) -> 0 | U61: =SUM(U54:U60) -> 0 | V61: =SUM(V54:V60) -> 0 | W61: =SUM(W54:W60) -> 257666.67 | X61: =SUM(X54:X60) -> 280930.67 | Y61: =SUM(Y54:Y60) -> 280930.67 | ... AB61: =SUM(AB54:AB60) -> 1497757.3
A63: DR | C63: Acquisition/ Capital Cost | D63: Maintenance/ Operating Cost | E63: Starting Year of Maint charges | F63: Discount % | G63: Unit of Measure | H63: Measured by | I63: conversion factor | J63: server | K63: socket | L63: core | O63: count | P63: Unit of Measure | Q63: Units | R63: 1 | S63: 2 | T63: 3 | U63: 4 | V63: 5 | W63: 1 | X63: 2 | Y63: 3 | Z63: 4 | AA63: 5 | AB63: TOT
A64: =A24 -> OS | C64: =C24 -> 0 | D64: =D24 -> 6000 | E64: =E24 -> 1 | F64: =F24 -> 0.2 | G64: =G54 -> core | H64: =H54 -> core | I64: =I54 -> 1 | J64: =$O$14 -> 0 | K64: =$P$14 -> 0 | L64: =$Q$14 -> 0 | O64: =_xlfn.XLOOKUP($H64,$J$23:$L$23,$J64:$L64) -> 0 | P64: socket | Q64: =I64*O64 -> 0 | R64: =$Q64*$C64*(1-$F64) -> 0 | W64: =IF(W$9<$E64,0,$Q64*$D64)*(1-$F64) -> 0 | X64: =IF(X$9<$E64,0,$Q64*$D64)*(1-$F64) -> 0 | Y64: =IF(Y$9<$E64,0,$Q64*$D64)*(1-$F64) -> 0 | Z64: =IF(Z$9<$E64,0,$Q64*$D64)*(1-$F64) -> 0 | AA64: =IF(AA$9<$E64,0,$Q64*$D64)*(1-$F64) -> 0 | AB64: =SUM(R64:AA64) -> 0
A65: =A25 -> VM | C65: =C25 -> 0 | D65: =D25 -> 0 | E65: =E25 -> 2 | F65: =F25 -> 0.2 | G65: =G55 -> core | H65: =H55 -> core | I65: =I55 -> 1 | J65: =J64 -> 0 | K65: =K64 -> 0 | L65: =L64 -> 0 | O65: =_xlfn.XLOOKUP($H65,$J$23:$L$23,$J65:$L65) -> 0 | P65: socket | Q65: =I65*O65 -> 0 | R65: =$Q65*$C65*(1-$F65) -> 0 | W65: =IF(W$9<$E65,0,$Q65*$D65)*(1-$F65) -> 0 | X65: =IF(X$9<$E65,0,$Q65*$D65)*(1-$F65) -> 0 | Y65: =IF(Y$9<$E65,0,$Q65*$D65)*(1-$F65) -> 0 | Z65: =IF(Z$9<$E65,0,$Q65*$D65)*(1-$F65) -> 0 | AA65: =IF(AA$9<$E65,0,$Q65*$D65)*(1-$F65) -> 0 | AB65: =SUM(R65:AA65) -> 0
A66: =A26 -> Application Server | C66: =C26 -> 46.82 | D66: =D26 -> 9.36 | E66: =E26 -> 2 | F66: =F26 -> 0.5 | G66: =G56 -> PVU | H66: =H56 -> core | I66: =I56 -> 120 | J66: =J65 -> 0 | K66: =K65 -> 0 | L66: =L65 -> 0 | O66: =_xlfn.XLOOKUP($H66,$J$23:$L$23,$J66:$L66) -> 0 | P66: PVU | Q66: =I66*O66 -> 0 | R66: =$Q66*$C66*(1-$F66) -> 0 | W66: =IF(W$9<$E66,0,$Q66*$D66)*(1-$F66) -> 0 | X66: =IF(X$9<$E66,0,$Q66*$D66)*(1-$F66) -> 0 | Y66: =IF(Y$9<$E66,0,$Q66*$D66)*(1-$F66) -> 0 | Z66: =IF(Z$9<$E66,0,$Q66*$D66)*(1-$F66) -> 0 | AA66: =IF(AA$9<$E66,0,$Q66*$D66)*(1-$F66) -> 0 | AB66: =SUM(R66:AA66) -> 0
A67: =A27 -> DB | C67: =C27 -> 0 | D67: =D27 -> 8500 | E67: =E27 -> 1 | F67: =F27 -> 0 | G67: =G57 -> server | H67: =H57 -> server | I67: =I57 -> 1 | J67: =J66 -> 0 | K67: =K66 -> 0 | L67: =L66 -> 0 | O67: =_xlfn.XLOOKUP($H67,$J$23:$L$23,$J67:$L67) -> 0 | P67: core | Q67: =I67*O67 -> 0 | R67: =$Q67*$C67*(1-$F67) -> 0 | W67: =IF(W$9<$E67,0,$Q67*$D67)*(1-$F67) -> 0 | X67: =IF(X$9<$E67,0,$Q67*$D67)*(1-$F67) -> 0 | Y67: =IF(Y$9<$E67,0,$Q67*$D67)*(1-$F67) -> 0 | Z67: =IF(Z$9<$E67,0,$Q67*$D67)*(1-$F67) -> 0 | AA67: =IF(AA$9<$E67,0,$Q67*$D67)*(1-$F67) -> 0 | AB67: =SUM(R67:AA67) -> 0
A68: =A28 -> Data Replication Tools | C68: =C28 -> 0 | D68: =D28 -> 3000 | E68: =E28 -> 1 | F68: =F28 -> 0.5 | G68: =G58 -> core | H68: =H58 -> core | I68: =I58 -> 1 | J68: =J67 -> 0 | K68: =K67 -> 0 | L68: =L67 -> 0 | O68: =_xlfn.XLOOKUP($H68,$J$23:$L$23,$J68:$L68) -> 0 | P68: core | Q68: =I68*O68 -> 0 | R68: =$Q68*$C68*(1-$F68) -> 0 | W68: =IF(W$9<$E68,0,$Q68*$D68)*(1-$F68) -> 0 | X68: =IF(X$9<$E68,0,$Q68*$D68)*(1-$F68) -> 0 | Y68: =IF(Y$9<$E68,0,$Q68*$D68)*(1-$F68) -> 0 | Z68: =IF(Z$9<$E68,0,$Q68*$D68)*(1-$F68) -> 0 | AA68: =IF(AA$9<$E68,0,$Q68*$D68)*(1-$F68) -> 0 | AB68: =SUM(R68:AA68) -> 0
A69: =A29 -> Monitoring Tools | C69: =C29 -> 5000 | D69: =D29 -> 1000 | E69: =E29 -> 2 | F69: =F29 -> 0.4 | G69: =G59 -> server | H69: =H59 -> server | I69: =I59 -> 1 | J69: =J68 -> 0 | K69: =K68 -> 0 | L69: =L68 -> 0 | O69: =_xlfn.XLOOKUP($H69,$J$23:$L$23,$J69:$L69) -> 0 | P69: server | Q69: =I69*O69 -> 0 | R69: =$Q69*$C69*(1-$F69) -> 0 | W69: =IF(W$9<$E69,0,$Q69*$D69)*(1-$F69) -> 0 | X69: =IF(X$9<$E69,0,$Q69*$D69)*(1-$F69) -> 0 | Y69: =IF(Y$9<$E69,0,$Q69*$D69)*(1-$F69) -> 0 | Z69: =IF(Z$9<$E69,0,$Q69*$D69)*(1-$F69) -> 0 | AA69: =IF(AA$9<$E69,0,$Q69*$D69)*(1-$F69) -> 0 | AB69: =SUM(R69:AA69) -> 0
A70: =A30 -> Security Tools | C70: =C30 -> 5000 | D70: =D30 -> 1000 | E70: =E30 -> 2 | F70: =F30 -> 0.4 | G70: =G60 -> server | H70: =H60 -> server | I70: =I60 -> 1 | J70: =J69 -> 0 | K70: =K69 -> 0 | L70: =L69 -> 0 | O70: =_xlfn.XLOOKUP($H70,$J$23:$L$23,$J70:$L70) -> 0 | P70: server | Q70: =I70*O70 -> 0 | R70: =$Q70*$C70*(1-$F70) -> 0 | W70: =IF(W$9<$E70,0,$Q70*$D70)*(1-$F70) -> 0 | X70: =IF(X$9<$E70,0,$Q70*$D70)*(1-$F70) -> 0 | Y70: =IF(Y$9<$E70,0,$Q70*$D70)*(1-$F70) -> 0 | Z70: =IF(Z$9<$E70,0,$Q70*$D70)*(1-$F70) -> 0 | AA70: =IF(AA$9<$E70,0,$Q70*$D70)*(1-$F70) -> 0 | AB70: =SUM(R70:AA70) -> 0
Q71: DR | R71: =SUM(R64:R70) -> 0 | S71: =SUM(S64:S70) -> 0 | T71: =SUM(T64:T70) -> 0 | U71: =SUM(U64:U70) -> 0 | V71: =SUM(V64:V70) -> 0 | W71: =SUM(W64:W70) -> 0 | X71: =SUM(X64:X70) -> 0 | Y71: =SUM(Y64:Y70) -> 0 | ... AB71: =SUM(AB64:AB70) -> 0
O73: Software Stack TOTALS | R73: =R31+R41+R51+R61+R71 -> 349104 | S73: =S31+S41+S51+S61+S71 -> 0 | T73: =T31+T41+T51+T61+T71 -> 0 | U73: =U31+U41+U51+U61+U71 -> 0 | V73: =V31+V41+V51+V61+V71 -> 0 | W73: =W31+W41+W51+W61+W71 -> 773000 | X73: =X31+X41+X51+X61+X71 -> 842792 | Y73: =Y31+Y41+Y51+Y61+Y71 -> 842792 | ... AB73: =AB31+AB41+AB51+AB61+AB71 -> 4493272 | AC73: TOT
A75: People
A76: People | O76: # of Server | P76: FTE Require | R76: 1 | S76: 2 | T76: 3 | U76: 4 | V76: 5 | W76: 1 | X76: 2 | Y76: 3 | Z76: 4 | AA76: 5 | AB76: TOT
A77: # of Servers covered by 1 FTE for IT Operations considering QoS | D77: 10 | E77: This is for patches, upgrade, backup, Crit Sit or Disaster recovery personnels, etc | N77: Prod | O77: =$O$10 -> 0.66666667 | P77: =$O77/$D$77 -> 0.066666667 | W77: =$D$78*$P77 -> 6666.6667 | X77: =$D$78*$P77 -> 6666.6667 | Y77: =$D$78*$P77 -> 6666.6667 | Z77: =$D$78*$P77 -> 6666.6667 | AA77: =$D$78*$P77 -> 6666.6667 | AB77: =SUM(R77:AA77) -> 33333.333 | AC77: Prod
A78: Avg yearly Fully loaded cost of IT Staff | D78: 100000 | N78: Dev | O78: =$O$11 -> 0.33333333 | P78: =$O78/$D$77 -> 0.033333333 | W78: =$D$78*$P78 -> 3333.3333 | X78: =$D$78*$P78 -> 3333.3333 | Y78: =$D$78*$P78 -> 3333.3333 | Z78: =$D$78*$P78 -> 3333.3333 | AA78: =$D$78*$P78 -> 3333.3333 | AB78: =SUM(R78:AA78) -> 16666.667 | AC78: Dev
N79: Test | O79: =$O$12 -> 0.33333333 | P79: =$O79/$D$77 -> 0.033333333 | W79: =$D$78*$P79 -> 3333.3333 | X79: =$D$78*$P79 -> 3333.3333 | Y79: =$D$78*$P79 -> 3333.3333 | Z79: =$D$78*$P79 -> 3333.3333 | AA79: =$D$78*$P79 -> 3333.3333 | AB79: =SUM(R79:AA79) -> 16666.667 | AC79: Test
N80: QA | O80: =$O$13 -> 0.66666667 | P80: =$O80/$D$77 -> 0.066666667 | W80: =$D$78*$P80 -> 6666.6667 | X80: =$D$78*$P80 -> 6666.6667 | Y80: =$D$78*$P80 -> 6666.6667 | Z80: =$D$78*$P80 -> 6666.6667 | AA80: =$D$78*$P80 -> 6666.6667 | AB80: =SUM(R80:AA80) -> 33333.333 | AC80: QA
N81: DR | O81: =$O$14 -> 0 | P81: =$O81/$D$77 -> 0 | W81: =$D$78*$P81 -> 0 | X81: =$D$78*$P81 -> 0 | Y81: =$D$78*$P81 -> 0 | Z81: =$D$78*$P81 -> 0 | AA81: =$D$78*$P81 -> 0 | AB81: =SUM(R81:AA81) -> 0 | AC81: DR
O82: TOT FTE required | P82: =SUM(P77:P81) -> 0.2 | R82: =SUM(R77:R81) -> 0 | S82: =SUM(S77:S81) -> 0 | T82: =SUM(T77:T81) -> 0 | U82: =SUM(U77:U81) -> 0 | V82: =SUM(V77:V81) -> 0 | W82: =SUM(W77:W81) -> 20000 | X82: =SUM(X77:X81) -> 20000 | Y82: =SUM(Y77:Y81) -> 20000 | ... AB82: =SUM(AB77:AB81) -> 100000 | AC82: TOT
A84: Network
A85: Network | P85: # of Server | R85: 1 | S85: 2 | T85: 3 | U85: 4 | V85: 5 | W85: 1 | X85: 2 | Y85: 3 | Z85: 4 | AA85: 5 | AB85: TOT
A86: Avg cost of Networking Infrastructure per Server | D86: 14000 | O86: Prod | P86: =$O$10 -> 0.66666667 | R86: =$P86*($D$86*(1-$D$87)) -> 6533.3333 | W86: =IF(W$85>=$D$90,$P86*($D$89*(1-$D$87)),0) -> 0 | X86: =IF(X$85>=$D$90,$P86*($D$89*(1-$D$87)),0) -> 653.33333 | Y86: =IF(Y$85>=$D$90,$P86*($D$89*(1-$D$87)),0) -> 653.33333 | Z86: =IF(Z$85>=$D$90,$P86*($D$89*(1-$D$87)),0) -> 653.33333 | AA86: =IF(AA$85>=$D$90,$P86*($D$89*(1-$D$87)),0) -> 653.33333 | AB86: =SUM(R86:AA86) -> 9146.6667 | AC86: Prod
A87: Avg discount % | D87: 0.3 | O87: Dev | P87: =$O$11 -> 0.33333333 | R87: =$P87*($D$86*(1-$D$87)) -> 3266.6667 | W87: =IF(W$85>=$D$90,$P87*($D$89*(1-$D$87)),0) -> 0 | X87: =IF(X$85>=$D$90,$P87*($D$89*(1-$D$87)),0) -> 326.66667 | Y87: =IF(Y$85>=$D$90,$P87*($D$89*(1-$D$87)),0) -> 326.66667 | Z87: =IF(Z$85>=$D$90,$P87*($D$89*(1-$D$87)),0) -> 326.66667 | AA87: =IF(AA$85>=$D$90,$P87*($D$89*(1-$D$87)),0) -> 326.66667 | AB87: =SUM(R87:AA87) -> 4573.3333 | AC87: Dev
A88: Avg Maintenance/ Operating Cost (% of acq.) | D88: 0.1 | O88: Test | P88: =$O$12 -> 0.33333333 | R88: =$P88*($D$86*(1-$D$87)) -> 3266.6667 | W88: =IF(W$85>=$D$90,$P88*($D$89*(1-$D$87)),0) -> 0 | X88: =IF(X$85>=$D$90,$P88*($D$89*(1-$D$87)),0) -> 326.66667 | Y88: =IF(Y$85>=$D$90,$P88*($D$89*(1-$D$87)),0) -> 326.66667 | Z88: =IF(Z$85>=$D$90,$P88*($D$89*(1-$D$87)),0) -> 326.66667 | AA88: =IF(AA$85>=$D$90,$P88*($D$89*(1-$D$87)),0) -> 326.66667 | AB88: =SUM(R88:AA88) -> 4573.3333 | AC88: Test
A89: Avg Maintenance/ Operating Cost (Currency) | D89: =D86*D88 -> 1400 | O89: QA | P89: =$O$13 -> 0.66666667 | R89: =$P89*($D$86*(1-$D$87)) -> 6533.3333 | W89: =IF(W$85>=$D$90,$P89*($D$89*(1-$D$87)),0) -> 0 | X89: =IF(X$85>=$D$90,$P89*($D$89*(1-$D$87)),0) -> 653.33333 | Y89: =IF(Y$85>=$D$90,$P89*($D$89*(1-$D$87)),0) -> 653.33333 | Z89: =IF(Z$85>=$D$90,$P89*($D$89*(1-$D$87)),0) -> 653.33333 | AA89: =IF(AA$85>=$D$90,$P89*($D$89*(1-$D$87)),0) -> 653.33333 | AB89: =SUM(R89:AA89) -> 9146.6667 | AC89: QA
A90: Starting Year of Maint | D90: 2 | O90: DR | P90: =$O$14 -> 0 | R90: =$P90*($D$86*(1-$D$87)) -> 0 | W90: =IF(W$85>=$D$90,$P90*($D$89*(1-$D$87)),0) -> 0 | X90: =IF(X$85>=$D$90,$P90*($D$89*(1-$D$87)),0) -> 0 | Y90: =IF(Y$85>=$D$90,$P90*($D$89*(1-$D$87)),0) -> 0 | Z90: =IF(Z$85>=$D$90,$P90*($D$89*(1-$D$87)),0) -> 0 | AA90: =IF(AA$85>=$D$90,$P90*($D$89*(1-$D$87)),0) -> 0 | AB90: =SUM(R90:AA90) -> 0 | AC90: DR
O91: TOT # of Servers | P91: =SUM(P86:P90) -> 2 | R91: =SUM(R86:R90) -> 19600 | S91: =SUM(S86:S90) -> 0 | T91: =SUM(T86:T90) -> 0 | U91: =SUM(U86:U90) -> 0 | V91: =SUM(V86:V90) -> 0 | W91: =SUM(W86:W90) -> 0 | X91: =SUM(X86:X90) -> 1960 | Y91: =SUM(Y86:Y90) -> 1960 | ... AB91: =SUM(AB86:AB90) -> 27440 | AC91: TOT
A93: Facilities
A94: Space | O94: # of Server | P94: # of Rack Cab | Q94: Avg. Footprint | R94: 1 | S94: 2 | T94: 3 | U94: 4 | V94: 5 | W94: 1 | X94: 2 | Y94: 3 | Z94: 4 | AA94: 5 | AB94: TOT
A95: Footprint of Server Rack Cabinet | C95: sq.m. | D95: 2.6 | N95: Prod | O95: =$O$10 -> 0.66666667 | P95: =$O95 -> 0.66666667 | Q95: =$P95*$D$95 -> 1.7333333 | W95: =$Q95*$D$97 -> 5726.9333 | X95: =$Q95*$D$97 -> 5726.9333 | Y95: =$Q95*$D$97 -> 5726.9333 | Z95: =$Q95*$D$97 -> 5726.9333 | AA95: =$Q95*$D$97 -> 5726.9333 | AB95: =SUM(R95:AA95) -> 28634.667 | AC95: Prod
N96: Dev | O96: =$O$11 -> 0.33333333 | P96: =$O96 -> 0.33333333 | Q96: =$P96*$D$95 -> 0.86666667 | W96: =$Q96*$D$97 -> 2863.4667 | X96: =$Q96*$D$97 -> 2863.4667 | Y96: =$Q96*$D$97 -> 2863.4667 | Z96: =$Q96*$D$97 -> 2863.4667 | AA96: =$Q96*$D$97 -> 2863.4667 | AB96: =SUM(R96:AA96) -> 14317.333 | AC96: Dev
A97: Fully loaded cost of space per sq meter | C97: € | D97: =2800*Data!C1 -> 3304 | N97: Test | O97: =$O$12 -> 0.33333333 | P97: =$O97 -> 0.33333333 | Q97: =$P97*$D$95 -> 0.86666667 | W97: =$Q97*$D$97 -> 2863.4667 | X97: =$Q97*$D$97 -> 2863.4667 | Y97: =$Q97*$D$97 -> 2863.4667 | Z97: =$Q97*$D$97 -> 2863.4667 | AA97: =$Q97*$D$97 -> 2863.4667 | AB97: =SUM(R97:AA97) -> 14317.333 | AC97: Test
N98: QA | O98: =$O$13 -> 0.66666667 | P98: =$O98 -> 0.66666667 | Q98: =$P98*$D$95 -> 1.7333333 | W98: =$Q98*$D$97 -> 5726.9333 | X98: =$Q98*$D$97 -> 5726.9333 | Y98: =$Q98*$D$97 -> 5726.9333 | Z98: =$Q98*$D$97 -> 5726.9333 | AA98: =$Q98*$D$97 -> 5726.9333 | AB98: =SUM(R98:AA98) -> 28634.667 | AC98: QA
N99: DR | O99: =$O$14 -> 0 | P99: =$O99 -> 0 | Q99: =$P99*$D$95 -> 0 | W99: =$Q99*$D$97 -> 0 | X99: =$Q99*$D$97 -> 0 | Y99: =$Q99*$D$97 -> 0 | Z99: =$Q99*$D$97 -> 0 | AA99: =$Q99*$D$97 -> 0 | AB99: =SUM(R99:AA99) -> 0 | AC99: DR
O100: =SUM(O95:O99) -> 2 | P100: =SUM(P95:P99) -> 2 | Q100: =SUM(Q95:Q99) -> 5.2 | R100: =SUM(R95:R99) -> 0 | S100: =SUM(S95:S99) -> 0 | T100: =SUM(T95:T99) -> 0 | U100: =SUM(U95:U99) -> 0 | V100: =SUM(V95:V99) -> 0 | ... AB100: =SUM(AB95:AB99) -> 85904 | AC100: TOT
O101: # of Server | P101: # of Rack Cab | Q101: Avg. Footprint
A103: Electricity | O103: # of Servers | P103: kWh / year | R103: 1 | S103: 2 | T103: 3 | U103: 4 | V103: 5 | W103: 1 | X103: 2 | Y103: 3 | Z103: 4 | AA103: 5 | AB103: TOT
A104: Actual Electricity Cost at the sites | C104: €/kWh | D104: =0.1*Data!C1 -> 0.118 | I104: Electricity Consumption by fully loaded z Server | J104: kWh | K104: =K5 -> 15 | N104: Prod | O104: =$O$10 -> 0.66666667 | P104: =$D$107*O104 -> 27663.158 | W104: =$P104*$D$104 -> 3264.2526 | X104: =$P104*$D$104 -> 3264.2526 | Y104: =$P104*$D$104 -> 3264.2526 | Z104: =$P104*$D$104 -> 3264.2526 | AA104: =$P104*$D$104 -> 3264.2526 | AB104: =SUM(R104:AA104) -> 16321.263 | AC104: Prod
A105: Electricity Additional Cost for cooling, UPS and other peripherals | C105: % | D105: 0.66 | I105: Electricity by core | J105: kWh | K105: =K104/H5 -> 0.078947368 | N105: Dev | O105: =$O$11 -> 0.33333333 | P105: =$D$107*O105 -> 13831.579 | W105: =$P105*$D$104 -> 1632.1263 | X105: =$P105*$D$104 -> 1632.1263 | Y105: =$P105*$D$104 -> 1632.1263 | Z105: =$P105*$D$104 -> 1632.1263 | AA105: =$P105*$D$104 -> 1632.1263 | AB105: =SUM(R105:AA105) -> 8160.6316 | AC105: Dev
A106: Electricity Consumption of Selected Server | C106: kWh | D106: =(K107*K105) -> 4.7368421 | N106: Test | O106: =$O$12 -> 0.33333333 | P106: =$D$107*O106 -> 13831.579 | W106: =$P106*$D$104 -> 1632.1263 | X106: =$P106*$D$104 -> 1632.1263 | Y106: =$P106*$D$104 -> 1632.1263 | Z106: =$P106*$D$104 -> 1632.1263 | AA106: =$P106*$D$104 -> 1632.1263 | AB106: =SUM(R106:AA106) -> 8160.6316 | AC106: Test
A107: Yearly kWh/ server | C107: kWh | D107: =$D$106*24*365 -> 41494.737 | I107: Number of cores | K107: =F15 -> 60 | N107: QA | O107: =$O$13 -> 0.66666667 | P107: =$D$107*O107 -> 27663.158 | W107: =$P107*$D$104 -> 3264.2526 | X107: =$P107*$D$104 -> 3264.2526 | Y107: =$P107*$D$104 -> 3264.2526 | Z107: =$P107*$D$104 -> 3264.2526 | AA107: =$P107*$D$104 -> 3264.2526 | AB107: =SUM(R107:AA107) -> 16321.263 | AC107: QA
N108: DR | O108: =$O$14 -> 0 | P108: =$D$107*O108 -> 0 | W108: =$P108*$D$104 -> 0 | X108: =$P108*$D$104 -> 0 | Y108: =$P108*$D$104 -> 0 | Z108: =$P108*$D$104 -> 0 | AA108: =$P108*$D$104 -> 0 | AB108: =SUM(R108:AA108) -> 0 | AC108: DR
O109: =SUM(O104:O108) -> 2 | P109: =SUM(P104:P108) -> 82989.474 | R109: =SUM(R104:R108) -> 0 | S109: =SUM(S104:S108) -> 0 | T109: =SUM(T104:T108) -> 0 | U109: =SUM(U104:U108) -> 0 | V109: =SUM(V104:V108) -> 0 | W109: =SUM(W104:W108) -> 9792.7579 | X109: =SUM(X104:X108) -> 9792.7579 | Y109: =SUM(Y104:Y108) -> 9792.7579 | ... AB109: =SUM(AB104:AB108) -> 48963.789 | AC109: TOT
O110: # of Servers | P110: kWh / year
N121: Prod | R121: =R95+R104+R113 -> 0 | S121: =S95+S104+S113 -> 0 | T121: =T95+T104+T113 -> 0 | U121: =U95+U104+U113 -> 0 | V121: =V95+V104+V113 -> 0 | W121: =W95+W104+W113 -> 8991.186 | X121: =X95+X104+X113 -> 8991.186 | Y121: =Y95+Y104+Y113 -> 8991.186 | ... AB121: =AB95+AB104+AB113 -> 44955.93 | AC121: Prod
N122: Dev | R122: =R96+R105+R114 -> 0 | S122: =S96+S105+S114 -> 0 | T122: =T96+T105+T114 -> 0 | U122: =U96+U105+U114 -> 0 | V122: =V96+V105+V114 -> 0 | W122: =W96+W105+W114 -> 4495.593 | X122: =X96+X105+X114 -> 4495.593 | Y122: =Y96+Y105+Y114 -> 4495.593 | ... AB122: =AB96+AB105+AB114 -> 22477.965 | AC122: Dev
N123: Test | R123: =R97+R106+R115 -> 0 | S123: =S97+S106+S115 -> 0 | T123: =T97+T106+T115 -> 0 | U123: =U97+U106+U115 -> 0 | V123: =V97+V106+V115 -> 0 | W123: =W97+W106+W115 -> 4495.593 | X123: =X97+X106+X115 -> 4495.593 | Y123: =Y97+Y106+Y115 -> 4495.593 | ... AB123: =AB97+AB106+AB115 -> 22477.965 | AC123: Test
N124: QA | R124: =R98+R107+R116 -> 0 | S124: =S98+S107+S116 -> 0 | T124: =T98+T107+T116 -> 0 | U124: =U98+U107+U116 -> 0 | V124: =V98+V107+V116 -> 0 | W124: =W98+W107+W116 -> 8991.186 | X124: =X98+X107+X116 -> 8991.186 | Y124: =Y98+Y107+Y116 -> 8991.186 | ... AB124: =AB98+AB107+AB116 -> 44955.93 | AC124: QA
N125: DR | R125: =R99+R108+R117 -> 0 | S125: =S99+S108+S117 -> 0 | T125: =T99+T108+T117 -> 0 | U125: =U99+U108+U117 -> 0 | V125: =V99+V108+V117 -> 0 | W125: =W99+W108+W117 -> 0 | X125: =X99+X108+X117 -> 0 | Y125: =Y99+Y108+Y117 -> 0 | ... AB125: =AB99+AB108+AB117 -> 0 | AC125: DR
...

Sheet TCO comparison
B1: Workload [TPS]= | C1: =sizing!C2 -> 8000
B3: x86 | C3: Environments | K3: LinuxONE | L3: Environments
A4: ='x86 TCO'!A5 -> Rack HPE w Xeon Gold 6230 20C 2.10GHz (2 Chips, 40 Cores) | C4: Prod | D4: Dev | E4: Test | F4: PreProd/QA | G4: DR | H4: Tot by Comp | L4: Prod | M4: Dev | N4: Test | O4: PreProd/QA | P4: DR | Q4: Tot by Comp
A5: Components | B5: Hardware | C5: ='x86 TCO'!AB19 -> 134400 | D5: ='x86 TCO'!AB20 -> 67200 | E5: ='x86 TCO'!AB21 -> 67200 | F5: ='x86 TCO'!AB22 -> 134400 | G5: ='x86 TCO'!AB23 -> 268800 | H5: =SUM(C5:G5) -> 672000 | J5: Components | K5: Hardware | L5: ='LinuxONE TCO'!AB10 -> 1848000 | M5: ='LinuxONE TCO'!AB11 -> 924000 | N5: ='LinuxONE TCO'!AB12 -> 924000 | O5: ='LinuxONE TCO'!AB13 -> 1848000 | P5: ='LinuxONE TCO'!AB14 -> 336000 | Q5: =SUM(L5:P5) -> 5880000
B6: Software | C6: ='x86 TCO'!AB35 -> 2612184 | D6: ='x86 TCO'!AB45 -> 1306092 | E6: ='x86 TCO'!AB55 -> 1306092 | F6: ='x86 TCO'!AB65 -> 2612184 | G6: ='x86 TCO'!AB75 -> 5224368 | H6: =SUM(C6:G6) -> 13060920 | K6: Software | L6: ='LinuxONE TCO'!AB31 -> 1497757.3 | M6: ='LinuxONE TCO'!AB41 -> 748878.67 | N6: ='LinuxONE TCO'!AB51 -> 748878.67 | O6: ='LinuxONE TCO'!AB61 -> 1497757.3 | P6: ='LinuxONE TCO'!AB71 -> 0 | Q6: =SUM(L6:P6) -> 4493272
B7: People | C7: ='x86 TCO'!AB86 -> 1000000 | H7: =SUM(C7:G7) -> 1000000 | K7: People | L7: ='LinuxONE TCO'!AB82 -> 100000 | Q7: =SUM(L7:P7) -> 100000
B8: Network | C8: ='x86 TCO'!AB90 -> 82320 | D8: ='x86 TCO'!AB91 -> 41160 | E8: ='x86 TCO'!AB92 -> 41160 | F8: ='x86 TCO'!AB93 -> 82320 | G8: ='x86 TCO'!AB94 -> 164640 | H8: =SUM(C8:G8) -> 411600 | K8: Network | L8: ='LinuxONE TCO'!AB86 -> 9146.6667 | M8: ='LinuxONE TCO'!AB87 -> 4573.3333 | N8: ='LinuxONE TCO'!AB88 -> 4573.3333 | O8: ='LinuxONE TCO'!AB89 -> 9146.6667 | P8: ='LinuxONE TCO'!AB90 -> 0 | Q8: =SUM(L8:P8) -> 27440
B9: Space | C9: ='x86 TCO'!AB99 -> 46020 | D9: ='x86 TCO'!AB100 -> 15953.6 | E9: ='x86 TCO'!AB101 -> 15953.6 | F9: ='x86 TCO'!AB102 -> 31907.2 | G9: ='x86 TCO'!AB103 -> 76700 | H9: =SUM(C9:G9) -> 186534.4 | K9: Space | L9: ='LinuxONE TCO'!AB95 -> 28634.667 | M9: ='LinuxONE TCO'!AB96 -> 14317.333 | N9: ='LinuxONE TCO'!AB97 -> 14317.333 | O9: ='LinuxONE TCO'!AB98 -> 28634.667 | P9: ='LinuxONE TCO'!AB99 -> 0 | Q9: =SUM(L9:P9) -> 85904
B10: Electricity | C10: ='x86 TCO'!AB108 -> 99233.28 | D10: ='x86 TCO'!AB109 -> 49616.64 | E10: ='x86 TCO'!AB110 -> 49616.64 | F10: ='x86 TCO'!AB111 -> 99233.28 | G10: ='x86 TCO'!AB112 -> 198466.56 | H10: =SUM(C10:G10) -> 496166.4 | K10: Electricity | L10: ='LinuxONE TCO'!AB104 -> 16321.263 | M10: ='LinuxONE TCO'!AB105 -> 8160.6316 | N10: ='LinuxONE TCO'!AB106 -> 8160.6316 | O10: ='LinuxONE TCO'!AB107 -> 16321.263 | P10: ='LinuxONE TCO'!AB108 -> 0 | Q10: =SUM(L10:P10) -> 48963.789
B11: Total by Env | C11: =SUM(C5:C10) -> 3974157.3 | D11: =SUM(D5:D10) -> 1480022.2 | E11: =SUM(E5:E10) -> 1480022.2 | F11: =SUM(F5:F10) -> 2960044.5 | G11: =SUM(G5:G10) -> 5932974.6 | H11: =SUM(H5:H10) -> 15827221 | K11: Total by Env | L11: =SUM(L5:L10) -> 3499859.9 | M11: =SUM(M5:M10) -> 1699930 | N11: =SUM(N5:N10) -> 1699930 | O11: =SUM(O5:O10) -> 3399859.9 | P11: =SUM(P5:P10) -> 336000 | Q11: =SUM(Q5:Q10) -> 10635580
P12: Savings = | Q12: =(H11-Q11)/H11 -> 0.32801975
B15: Hardware | C15: Software | D15: People | E15: Network | F15: Facilities | G15: DR | H15: TOT
A16: =B3 -> x86 | B16: =SUM(C5:F5) -> 403200 | C16: =SUM(C6:F6) -> 7836552 | D16: =SUM(C7:F7) -> 1000000 | E16: =SUM(#REF!) -> #REF! | F16: =SUM(#REF!) -> #REF! | G16: =G11 -> 5932974.6 | H16: =SUM(B16:G16) -> #REF!
A17: =K3 -> LinuxONE | B17: =SUM(L5:O5) -> 5544000 | C17: =SUM(L6:O6) -> 4493272 | D17: =SUM(L7:O7) -> 100000 | E17: =SUM(#REF!) -> #REF! | F17: =SUM(#REF!) -> #REF! | G17: =P11 -> 336000 | H17: =SUM(B17:G17) -> #REF!
B19: Cumulative Costs | C19: Year 1 | D19: Year 2 | E19: Year 3 | F19: Year 4 | G19: Year 5
B20: =B3 -> x86 | C20: ='x86 TCO'!W126 -> 5518980.2 | D20: ='x86 TCO'!X126 -> 8048040.3 | E20: ='x86 TCO'!Y126 -> 10577100 | F20: ='x86 TCO'!Z126 -> 13202161 | G20: ='x86 TCO'!AA126 -> 15827221
B21: =K3 -> LinuxONE | C21: ='LinuxONE TCO'!W131 -> 6088677.6 | D21: ='LinuxONE TCO'!X131 -> 6980403.1 | E21: ='LinuxONE TCO'!Y131 -> 7872128.7 | F21: ='LinuxONE TCO'!Z131 -> 9253854.2 | G21: ='LinuxONE TCO'!AA131 -> 10635580
B31: TCA (1st year) | C31: Hardware | D31: Software | E31: TOT
B32: x86 | C32: ='x86 TCO'!R24 -> 480000 | D32: ='x86 TCO'!R35 -> 561288 | E32: =SUM(C32:D32) -> 1041288
B33: LinuxONE | C33: ='LinuxONE TCO'!R15 -> 4900000 | D33: ='LinuxONE TCO'!R31 -> 116368 | E33: =SUM(C33:D33) -> 5016368 | F33: =E33/E32 -> 4.8174645

Sheet Data
A1: Warmup Tasks | B1: € - $ Rate 25/03/21 | C1: 1.18
A3: Server
A4: Server Model | B4: Acquisition Cost | C4: Maintenance/ Operating Cost | D4: Starting Year of Maint | E4: Discount % | F4: # of Cores per Server | G4: # of Sockets | H4: # of Cores per socket | I4: # of "boxes" per Rack | J4: kW | K4: PVU* | L4: Source
A5: Rack DELL w Xeon Gold 5220 18C 2.20GHz (4 Chips, 72 Cores) | B5: =ROUND(24549/C1, -2) -> 20800 | C5: =B5*0.2 -> 4160 | D5: 4 | E5: 0.37 | F5: =G5*H5 -> 72 | G5: 4 | H5: 18 | I5: 10 | J5: 1.1 | K5: 100 | L5: https://www.dell.com/en-us/work/shop/cty/pdp/spd/poweredge-r940/pe_r940_12229_vi_vp?configurationid=98797f27-d554-4678-b6d3-e9240afd88af
A6: Rack HPE w Xeon Gold 6230 20C 2.10GHz (2 Chips, 40 Cores) | B6: 8000 | C6: =B6*0.2 -> 1600 | D6: 4 | E6: 0 | F6: =G6*H6 -> 40 | G6: 2 | H6: 20 | I6: 15 | J6: 1.6 | K6: 70 | L6: https://buy.hpe.com/it/it/servers/proliant-dl-servers/proliant-dl500-servers/proliant-dl560-server/hpe-proliant-dl560-gen10-server/hpe-proliant-dl560-gen10-6230-2-1ghz-20-core-2p-128gb-r-8sff-2x1600w-rps-server/p/P40455-B21
A8: * https://www.ibm.com/software/passportadvantage/pvu_licensing_for_customers.html
A10: Application Server
A12: {=INDEX(A15:A21,$G$12)} -> IBM WebSphere | B12: {=INDEX(B15:B21,$G$12)} -> 46.82 | C12: {=INDEX(C15:C21,$G$12)} -> 9.36 | D12: {=INDEX(D15:D21,$G$12)} -> 2 | E12: {=INDEX(F15:F21,$G$12)} -> PVU | F12: {=INDEX(G15:G21,$G$12)} -> core | G12: =MATCH("S",O15:O21) -> 2
A13: Commercial Application Server
A14: Name | B14: Acquisition Cost | C14: Maintenance/ Operating Cost | D14: Starting Year of yearly charges | E14: Discount % | F14: Unit of Measure | G14: Measured by | H14: conversion factor | I14: Source
A15: WebLogic Server Enterprise Edition | B15: =ROUND(25000/C1, -2) -> 21200 | C15: =ROUND(5500/C1, -2) -> 4700 | D15: 1 | E15: 0 | F15: core | G15: core | H15: 0.5 | I15: https://www.oracle.com/assets/technology-price-list-070617.pdf | O15: 0
A16: IBM WebSphere | B16: =ROUND(55.25/C1, 2) -> 46.82 | C16: =ROUND(B16*20/100, 2) -> 9.36 | D16: 2 | E16: 0 | F16: PVU | G16: core | H16: * | I16: https://reviews.financesonline.com/p/ibm-webspehre/ | O16: S
A18: Open Source Application Server
A19: Name | B19: Acquisition Cost | C19: Maintenance/ Operating Cost | D19: Starting Year of yearly charges | E19: Discount % | F19: Unit of Measure | G19: Measured by | H19: conversion factor | I19: Source
A20: JBoss Enterprise Application Platform | B20: 0 | C20: =ROUND(12000/C1, -2) -> 10200 | D20: 1 | E20: 0 | F20: core | G20: core | H20: 0.0625 | I20: https://www.redhat.com/en/store/red-hat-jboss-enterprise-application-platform | O20: 0
A21: Payara Server Enterprise | B21: 0 | C21: Contact us | D21: - | E21: - | F21: - | G21: - | H21: - | I21: https://www.payara.fish/page/payara-enterprise-downloads/ | O21: 0
A23: Database
A25: {=INDEX(A28:A34,$G$25)} -> MongoDB | B25: {=INDEX(B28:B34,$G$25)} -> 0 | C25: {=INDEX(C28:C34,$G$25)} -> 8500 | D25: {=INDEX(D28:D34,$G$25)} -> 1 | E25: {=INDEX(F28:F34,$G$25)} -> server | F25: {=INDEX(G28:G34,$G$25)} -> server | G25: =MATCH("S",R28:R34) -> 6
A26: Commercial Database
A27: Name | B27: Acquisition Cost | C27: Maintenance/ Operating Cost | D27: Starting Year of yearly charges | E27: Discount % | F27: Unit of Measure | G27: Measured by | H27: conversion factor | I27: Data replication tool | J27: Source
A28: Oracle Database Enterprise Edition | B28: =ROUND(47500/C1, -2) -> 40300 | C28: =ROUND(10450/C1, -2) -> 8900 | D28: 1 | E28: 0 | F28: core | G28: core | H28: 0.5 | I28: =_xlfn.CONCAT(ROUND(3500/C1,-2), " / stream") -> 3000 / stream | J28: https://www.oracle.com/assets/technology-price-list-070617.pdf | R28: 0
A29: Microsoft SQL Server 2019 | B29: =ROUND(13748/C1, -2) -> 11700 | C29: =B29*20/100 -> 2340 | D29: 1 | E29: 0 | F29: core | G29: core | H29: 0.5 | I29: A30 | J29: https://www.microsoft.com/en-us/sql-server/sql-server-2019-pricing | R29: 0
A31: Open Source Database
A32: Name | B32: Acquisition Cost | C32: Maintenance/ Operating Cost | D32: Starting Year of yearly charges | E32: Discount % | F32: Unit of Measure | G32: Measured by | H32: conversion factor | I32: Data replication tool | J32: Source
A33: MongoDB | B33: 0 | C33: =ROUND(10000/C1,-2) -> 8500 | D33: 1 | E33: 0 | F33: server | G33: server | H33: 1 | I33: A31 | J33: https://www.pcworld.com/article/2466460/mongodb-adds-support-option-for-community-edition-of-its-nosql-database.html | R33: S
A34: SQLite | B34: 0 | C34: =ROUND(85000/C1,-2) -> 72000 | D34: 1 | E34: 0 | F34: year | G34: year | H34: 1 | I34: A32 | J34: https://www.sqlite.org/prosupport.html | R34: 0
A36: https://docs.microsoft.com/it-it/sql/relational-databases/replication/configure-publishing-and-distribution?view=sql-server-ver15 | F36: 0 | H36: All conversion factors are for x86 cores
A37: https://docs.mongodb.com/manual/tutorial/deploy-replica-set/ | F37: 0 | H37: Remember to change discount and conversion factor in each TCO
A38: https://github.com/benbjohnson/litestream | F38: 0
A40: Another reference for MongoDB
A41: https://www.reddit.com/r/mongodb/comments/a3xvaw/mongodb_enterprise_pricing/
C44: TCO at 5y 1 fault by TPS
C46: 100 | D46: 200 | E46: 500 | F46: 1000
B47: x86 | C47: 859910.94 | D47: 1042588.4 | E47: 2069664.3 | F47: 3492667.7
B48: LinuxONE | C48: 1484198.5 | D48: 1484198.5 | E48: 1722780.3 | F48: 2129362.1
